Workbook

Sheet 00_README
A1: TIFS Critical Review — Detailed Audit Workbook
A2: Prefilled from the current “From Sound to Shelf” manuscript and supplementary package. Blue-font cells are intended for author input; formula cells are black.
A4: Purpose and use
A5: Workbook purpose | B5: Audit scientific logic, evidence support, review-method integrity, writing quality, visuals, references and TIFS submission readiness.
A6: Central paper idea | B6: A transferable acoustic process must be defined by the exposure received by the fruit—not by repeated source settings.
A7: Source files | B7: From_Sound_to_Shelf_TIFS_Critical_Review_Rewritten.docx; From_Sound_to_Shelf_TIFS_Supplementary_Material.docx; How-to-write-a-great-research-paper PDF; scientific-writing guidance documents.
A8: Evidence boundary | B8: No missing sample sizes, screening counts, effect sizes or experimental results were invented. Unverified fields are marked for completion.
A9: Recommended workflow | B9: 1) Start on Dashboard; 2) resolve Critical actions; 3) verify Claim–Evidence ledger; 4) finish search / reference audit; 5) close figure and table actions; 6) rerun writing audit; 7) complete TIFS compliance.
A11: Scoring scale
A12: Score | B12: Meaning | C12: Operational definition
A13: 0 | B13: Missing / unsupported | C13: Required element absent or claim unsupported.
A14: 1 | B14: Weak | C14: Present but materially inadequate or contradicted.
A15: 2 | B15: Partial | C15: Useful foundation; important verification or revision remains.
A16: 3 | B16: Strong | C16: Scientifically defensible; minor refinement remains.
A17: 4 | B17: Submission-ready | C17: Complete, verified, reproducible and internally consistent.
A19: Colour and cell conventions
A20: Blue font / pale yellow fill | B20: Author input or field that must be completed from records.
A21: Green font | B21: Imported or source-derived content.
A22: Black font | B22: Formula, derived result or completed audit judgement.
A23: Orange fill | B23: Caution / revision needed.
A24: Light red fill | B24: Critical error, unsupported claim or blocking issue.
A25: Purple fill | B25: Control logic, criteria or decision rule.
A26: Teal fill | B26: Key scientific KPI, framework element or visualization anchor.
A29: Sheet map
A30: 01_Dashboard | B30: Submission-readiness KPIs and blocking issues.
A31: 02_Story_Audit | B31: One-line problem, one ping, title, novelty, contribution and scope audit.
A32: 03_Section_Audit | B32: Section-by-section function, strengths, gaps and actions.
A33: 04_Claim_Evidence | B33: Claim-to-evidence ledger with overclaim and qualifier controls.
A34: 05_Study_Comparison | B34: Detailed seven-study comparison matrix.
A35: 06_Evidence_Chain | B35: A–D causal-link heatmap and domain summaries.
A36: 07_Contradictions | B36: Contradictions, hidden variables and decisive tests.
A37: 08_Gaps_Innovations | B37: High-value gaps, experiments, impact and prioritization.
A38: 09_Figure_Audit | B38: Graphical abstract, main and supplementary figure audit.
A39: 10_Table_Audit | B39: Main and supplementary table audit.
A40: 11_Supplement_Audit | B40: Supplementary package completeness and non-duplication audit.
A41: 12_Reference_Audit | B41: All references with verification and claim-support fields.
... A46: 17_Decision_Log | B46: Scope and positioning decisions for co-author alignment.

Sheet 01_Dashboard
A1: TIFS Critical Review Audit Dashboard
A2: Overall readiness reflects scientific integrity, evidence verification, visual package, writing quality and submission compliance.
A4: Overall readiness | E4: Critical open actions | I4: Claims needing verification | P4: Action status
A5: =AVERAGE(C13:C19) | E5: =COUNTIFS('16_Action_Plan'!J4:J17,"Critical",'16_Action_Plan'!L4:L17,"<>Complete") | I5: =COUNTIF('04_Claim_Evidence'!N4:N28,"Needs verification") | P5: Not started | Q5: =COUNTIF('16_Action_Plan'!$L$4:$L$17,P5)
P6: In progress | Q6: =COUNTIF('16_Action_Plan'!$L$4:$L$17,P6)
A7: References not verified | E7: Evidence Grade-D cells | I7: TIFS compliance blockers | P7: Needs verification | Q7: =COUNTIF('16_Action_Plan'!$L$4:$L$17,P7)
A8: =COUNTIF('12_Reference_Audit'!Q4:Q130,"Needs verification") | E8: =COUNTIF('06_Evidence_Chain'!C8:I14,"D") | I8: =COUNTIFS('13_TIFS_Compliance'!H4:H25,"Critical",'13_TIFS_Compliance'!G4:G25,"<>Complete") | P8: Needs revision | Q8: =COUNTIF('16_Action_Plan'!$L$4:$L$17,P8)
P9: Complete | Q9: =COUNTIF('16_Action_Plan'!$L$4:$L$17,P9)
A11: Readiness by audit domain
A12: Domain | B12: Score / 4 | C12: Readiness % | D12: Open critical/high items | E12: Linked sheet | F12: Primary blocker | G12: Owner | H12: Status
A13: Story / positioning | B13: =ROUND(AVERAGE('02_Story_Audit'!E4:E20),2) | C13: ='02_Story_Audit'!B22/100 | D13: =COUNTIFS('02_Story_Audit'!I4:I20,"Critical",'02_Story_Audit'!H4:H20,"<>Complete")+COUNTIFS('02_Story_Audit'!I4:I20,"High",'02_Story_Audit'!H4:H20,"<>Complete") | E13: 02_Story_Audit | F13: Search reproducibility and novelty comparison | H13: In progress
A14: Section completeness | B14: =ROUND(AVERAGE('03_Section_Audit'!G4:G16),2) | C14: =B14/4 | D14: =COUNTIFS('03_Section_Audit'!I4:I16,"Critical",'03_Section_Audit'!H4:H16,"<>Complete")+COUNTIFS('03_Section_Audit'!I4:I16,"High",'03_Section_Audit'!H4:H16,"<>Complete") | E14: 03_Section_Audit | F14: Method, references and declarations | H14: In progress
A15: Claim support | B15: =ROUND(AVERAGE('04_Claim_Evidence'!P4:P28),2) | C15: =B15/4 | D15: =COUNTIFS('04_Claim_Evidence'!O4:O28,"Critical",'04_Claim_Evidence'!N4:N28,"<>Complete")+COUNTIFS('04_Claim_Evidence'!O4:O28,"High",'04_Claim_Evidence'!N4:N28,"<>Complete") | E15: 04_Claim_Evidence | F15: Corpus-bounded findings and overclaim control | H15: In progress
A16: Figures | B16: =ROUND(AVERAGE('09_Figure_Audit'!J4:L10),2) | C16: =B16/4 | D16: =COUNTIFS('09_Figure_Audit'!P4:P10,"Critical",'09_Figure_Audit'!O4:O10,"<>Complete")+COUNTIFS('09_Figure_Audit'!P4:P10,"High",'09_Figure_Audit'!O4:O10,"<>Complete") | E16: 09_Figure_Audit | F16: Figure 3 depends on verified evidence coding | H16: In progress
A17: Tables / supplement | B17: =ROUND(AVERAGE('10_Table_Audit'!R4:R11),2) | C17: =B17/4 | D17: =COUNTIFS('10_Table_Audit'!K4:K11,"Critical",'10_Table_Audit'!J4:J11,"<>Complete")+COUNTIFS('11_Supplement_Audit'!J4:J10,"Critical",'11_Supplement_Audit'!I4:I10,"<>Complete") | E17: 10_Table_Audit | F17: S1–S3 and S5 incomplete | H17: In progress
A18: References | B18: =IFERROR((COUNTIF('12_Reference_Audit'!Q4:Q130,"Complete")/COUNTA('12_Reference_Audit'!A4:A130))*4,0) | C18: =B18/4 | D18: =COUNTIFS('12_Reference_Audit'!P4:P130,"High",'12_Reference_Audit'!Q4:Q130,"<>Complete") | E18: 12_Reference_Audit | F18: Source-level verification pending | H18: Not started
A19: TIFS compliance | B19: =IFERROR((COUNTIF('13_TIFS_Compliance'!F4:F25,"Yes")/COUNTA('13_TIFS_Compliance'!A4:A25))*4,0) | C19: =B19/4 | D19: =COUNTIFS('13_TIFS_Compliance'!H4:H25,"Critical",'13_TIFS_Compliance'!G4:G25,"<>Complete") | E19: 13_TIFS_Compliance | F19: Current journal instructions and declarations | H19: Not started
A22: Top blocking actions
A23: Action ID | B23: Action | C23: Why it matters | D23: Priority | E23: Status | F23: Owner | G23: Due date | H23: Linked item
A24: ='16_Action_Plan'!A4 | B24: ='16_Action_Plan'!C4 | C24: ='16_Action_Plan'!D4 | D24: ='16_Action_Plan'!J4 | E24: ='16_Action_Plan'!L4 | F24: ='16_Action_Plan'!K4 | G24: ='16_Action_Plan'!M4 | H24: ='16_Action_Plan'!O4
A25: ='16_Action_Plan'!A5 | B25: ='16_Action_Plan'!C5 | C25: ='16_Action_Plan'!D5 | D25: ='16_Action_Plan'!J5 | E25: ='16_Action_Plan'!L5 | F25: ='16_Action_Plan'!K5 | G25: ='16_Action_Plan'!M5 | H25: ='16_Action_Plan'!O5
A26: ='16_Action_Plan'!A6 | B26: ='16_Action_Plan'!C6 | C26: ='16_Action_Plan'!D6 | D26: ='16_Action_Plan'!J6 | E26: ='16_Action_Plan'!L6 | F26: ='16_Action_Plan'!K6 | G26: ='16_Action_Plan'!M6 | H26: ='16_Action_Plan'!O6
A27: ='16_Action_Plan'!A7 | B27: ='16_Action_Plan'!C7 | C27: ='16_Action_Plan'!D7 | D27: ='16_Action_Plan'!J7 | E27: ='16_Action_Plan'!L7 | F27: ='16_Action_Plan'!K7 | G27: ='16_Action_Plan'!M7 | H27: ='16_Action_Plan'!O7
A28: ='16_Action_Plan'!A8 | B28: ='16_Action_Plan'!C8 | C28: ='16_Action_Plan'!D8 | D28: ='16_Action_Plan'!J8 | E28: ='16_Action_Plan'!L8 | F28: ='16_Action_Plan'!K8 | G28: ='16_Action_Plan'!M8 | H28: ='16_Action_Plan'!O8
A29: ='16_Action_Plan'!A9 | B29: ='16_Action_Plan'!C9 | C29: ='16_Action_Plan'!D9 | D29: ='16_Action_Plan'!J9 | E29: ='16_Action_Plan'!L9 | F29: ='16_Action_Plan'!K9 | G29: ='16_Action_Plan'!M9 | H29: ='16_Action_Plan'!O9
A30: ='16_Action_Plan'!A10 | B30: ='16_Action_Plan'!C10 | C30: ='16_Action_Plan'!D10 | D30: ='16_Action_Plan'!J10 | E30: ='16_Action_Plan'!L10 | F30: ='16_Action_Plan'!K10 | G30: ='16_Action_Plan'!M10 | H30: ='16_Action_Plan'!O10
A31: ='16_Action_Plan'!A11 | B31: ='16_Action_Plan'!C11 | C31: ='16_Action_Plan'!D11 | D31: ='16_Action_Plan'!J11 | E31: ='16_Action_Plan'!L11 | F31: ='16_Action_Plan'!K11 | G31: ='16_Action_Plan'!M11 | H31: ='16_Action_Plan'!O11
A32: ='16_Action_Plan'!A12 | B32: ='16_Action_Plan'!C12 | C32: ='16_Action_Plan'!D12 | D32: ='16_Action_Plan'!J12 | E32: ='16_Action_Plan'!L12 | F32: ='16_Action_Plan'!K12 | G32: ='16_Action_Plan'!M12 | H32: ='16_Action_Plan'!O12
A33: ='16_Action_Plan'!A13 | B33: ='16_Action_Plan'!C13 | C33: ='16_Action_Plan'!D13 | D33: ='16_Action_Plan'!J13 | E33: ='16_Action_Plan'!L13 | F33: ='16_Action_Plan'!K13 | G33: ='16_Action_Plan'!M13 | H33: ='16_Action_Plan'!O13

Sheet 02_Story_Audit
A1: Story, Positioning and “One Ping” Audit
A2: Score each item 0–4. The current judgements are prefilled from the manuscript; revise them after author verification.
A3: ID | B3: Audit item | C3: Submission standard | D3: Current manuscript evidence / formulation | E3: Score (0–4) | F3: Weight | G3: Weighted score | H3: Status | I3: Priority | J3: Required action | K3: Owner | L3: Due date | M3: Source / location | N3: Reviewer notes
A4: S01 | B4: One-line real problem | C4: Identifies a field-level, consequential problem—not merely a missing review. | D4: Acoustic treatments are specified by frequency, dB, power and time although these do not define receiver exposure. | E4: 4 | F4: 5 | G4: =E4*F4 | H4: High | I4: Keep wording identical in title logic, abstract, introduction, cover letter and conclusion. | L4: Introduction ¶1–5
A5: S02 | B5: One reusable “ping” | C5: Reader can repeat one sharp insight after closing the paper. | D5: The treatment is what the fruit receives, not what the machine emits. | E5: 4 | F5: 5 | G5: =E5*F5 | H5: Critical | I5: Prevent secondary ideas from competing with receiver exposure. | L5: Introduction / conclusion
A6: S03 | B6: Title–scope alignment | C6: Title states hook, contribution and bounded receiver. | D6: “From Sound to Shelf … Intact Fruit” aligns with mechanisms, evidence and process design. | E6: 4 | F6: 4 | G6: =E6*F6 | H6: Medium | I6: Retain “intact fruit”; avoid implying all food acoustic technologies are comprehensively reviewed. | L6: Title page
A7: S04 | B7: Concrete opening example | C7: Page one uses a memorable physical counterexample before abstraction. | D7: The 25 kHz example contrasts contact strain, cavitation, boundary-layer forcing and support motion. | E7: 4 | F7: 4 | G7: =E7*F7 | H7: High | I7: Keep Figure 1 visually consistent with this example. | L7: Introduction ¶1 / Figure 1
A8: S05 | B8: Quantified evidence gap | C8: Gap includes corpus-bounded quantitative result. | D8: 0/7 fruit motion; 0/7 support isolation; 0/7 external confirmation. | E8: 3 | F8: 5 | G8: =E8*F8 | H8: Critical | I8: Complete reproducible search and independent coding before finalizing the 0/7 claim. | L8: Table 2 / Figure 3 / Supplement
A9: S06 | B9: Novelty versus prior reviews | C9: States exactly how this review differs from ultrasound/application reviews. | D9: Mechanism- and receiver-centred taxonomy plus causal-closure audit and transfer test. | E9: 3 | F9: 5 | G9: =E9*F9 | H9: High | I9: Add a concise “difference from prior reviews” paragraph or comparison box. | L9: End of Introduction
A10: S07 | B10: Three refutable contributions | C10: Contributions are specific, evidence-linked and capable of failure. | D10: Reclassification; evidence-chain diagnosis; receiver-centred process design. | E10: 4 | F10: 5 | G10: =E10*F10 | H10: High | I10: Maintain only these three headline contributions. | L10: Introduction bullets
A11: S08 | B11: Central testable hypothesis | C11: Predictor and failure condition are explicit. | D11: Receiver motion / validated strain should outperform nominal source settings for a mechanical effect. | E11: 4 | F11: 5 | G11: =E11*F11 | H11: Critical | I11: Keep conditional wording; do not present as established fact. | L11: Introduction / Section 8
A12: S09 | B12: Failure conditions | C12: Paper states evidence that would weaken or reject the framework. | D12: Matched exposure without improved prediction implies an incomplete mechanism. | E12: 4 | F12: 4 | G12: =E12*F12 | H12: High | I12: Repeat failure condition in Figure 4 and conclusion. | L12: Table 3 / Section 8
A13: S10 | B13: Critical review position | C13: Paper compares, explains disagreement and separates fact from interpretation. | D13: Contradiction matrix links disagreement to hidden variables and decisive tests. | E13: 4 | F13: 4 | G13: =E13*F13 | H13: High | I13: Preserve neutral wording; avoid implying earlier results are false. | L13: Section 5 / Table 3
A14: S11 | B14: Scope boundary | C14: Primary receiver and comparator literatures are explicitly separated. | D14: Intact fruit is focal; sensing, liquid ultrasound, transport and mechanobiology are comparators. | E14: 4 | F14: 4 | G14: =E14*F14 | H14: High | I14: State this boundary in abstract and methods. | L14: Abstract / Section 2
A15: S12 | B15: Shelf relevance | C15: Outcome extends beyond single firmness values to longitudinal shelf performance. | D15: Section 7 defines trajectories, safety, damage and usable shelf period. | E15: 3 | F15: 4 | G15: =E15*F15 | H15: High | I15: Check that each shelf-performance claim has direct literature support and does not imply validated extension. | L15: Section 7
... A20: S17 | B20: TIFS fit | C20: Connects critical synthesis to food-industry application, scale-up and decisions. | D20: Mechanisms → evidence → process design → shelf performance. | E20: 4 | F20: 4 | G20: =E20*F20 | H20: High | I20: Keep plant physiology subordinate to food-process metrology. | L20: Whole manuscript
A22: Weighted readiness (%) | B22: =ROUND(SUM(G4:G20)/(4*SUM(F4:F20))*100,1)

Sheet 03_Section_Audit
A1: Section-by-Section Manuscript Audit
A2: Each section should perform one scientific job and move the narrative from mechanism to evidence to process design to shelf relevance.
A3: Section | B3: Primary job | C3: Current strength | D3: Principal weakness / risk | E3: Evidence or completion needed | F3: Current word count | G3: Score (0–4) | H3: Status | I3: Priority | J3: Required action | K3: Owner | L3: Due date | M3: Source / page | N3: Notes
A4: Highlights | B4: State five concise findings without overclaiming. | C4: Clear receiver-centred story and 0/7 signal. | D4: “None of seven” requires completed review protocol. | E4: Final search and coding record; final word/character limits. | F4: 51 | G4: 3 | H4: Needs verification | I4: High | J4: Verify journal format and evidence boundary. | M4: Manuscript
A5: Abstract | B5: Problem → gap → critical synthesis → framework → impact. | C5: Strong source-versus-receiver problem and quantified gap. | D5: Methods and 0/7 claim depend on unfinished search documentation. | E5: Final database record; exact abstract word limit check. | F5: 244 | G5: 3 | H5: Needs verification | I5: Critical | J5: Update only after search audit is locked. | M5: Manuscript
A6: 1. Introduction: the missing link from sound to shelf | B6: Concrete example, gap, position and three contributions. | C6: Excellent 25 kHz counterexample and refutable contributions. | D6: Novelty versus existing reviews could be more explicit. | E6: One compact prior-review comparison paragraph. | F6: 456 | G6: 4 | H6: Complete | I6: High | J6: Add explicit novelty comparison if space permits. | M6: Manuscript
A7: 2. Review scope and critical evidence method | B7: Define search, eligibility, grading and claim boundary. | C7: Honest question-led review boundary and grade definitions. | D7: Databases, counts, exclusions and reviewer agreement unfinished. | E7: Complete S1–S3 from actual records. | F7: 268 | G7: 2 | H7: Needs verification | I7: Critical | J7: Treat as the main submission blocker. | M7: Manuscript
A8: 3. Mechanisms: one acoustic spectrum, different physical technologies | B8: Reclassify technologies by transfer path and receiver variable. | C8: Strong physics-based taxonomy and 25 kHz example. | D8: Deployment judgements may appear subjective. | E8: Define maturity criteria or soften labels. | F8: 0 | G8: 3 | H8: Needs revision | I8: High | J8: Move detailed maturity rubric to supplement. | M8: Manuscript
A9: 4. Evidence: what is established and what remains latent | B9: Compare study clusters and audit causal closure. | C9: Distinguishes outcome evidence from exposure evidence. | D9: Seven studies are a narrow corpus and connected lineage. | E9: Search completeness; full-text verification; second reviewer. | F9: 0 | G9: 3 | H9: Needs verification | I9: Critical | J9: Lock extraction and evidence coding. | M9: Manuscript
A10: 5. Contradictions reveal hidden exposure variables | B10: Explain disagreement through hidden variables and decisive tests. | C10: High-value synthesis; not a paper-by-paper catalogue. | D10: Some comparator claims may require source-level verification. | E10: Claim–reference audit for every contradiction. | F10: 125 | G10: 3 | H10: Needs verification | I10: High | J10: Use Table 3 as the organizing spine. | M10: Manuscript
A11: 6. Receiver-centred process design | B11: Operationalize the solution. | C11: Exposure Passport, Operating Window and receiver equivalence are coherent. | D11: Proposed tools are not yet validated standards. | E11: Use “proposed”; distinguish minimum reporting from validation. | F11: 0 | G11: 4 | H11: Complete | I11: High | J11: Keep receiver equivalence explicitly testable. | M11: Manuscript
A12: 7. From treatment to shelf performance | B12: Connect exposure to longitudinal product value. | C12: Moves beyond single firmness endpoints. | D12: Risk of promising shelf-life extension without validation. | E12: Use “shelf-relevant trajectory”; support each outcome domain. | F12: 0 | G12: 3 | H12: Needs revision | I12: High | J12: Audit wording around shelf extension. | M12: Manuscript
A13: 8. Decisive experiments and staged validation | B13: Specify experiments that can support or reject the framework. | C13: Motion clamp and route separation produce informative outcomes. | D13: No pilot variance, sample size or equivalence margin yet. | E13: Pilot design and statistical analysis plan. | F13: 0 | G13: 3 | H13: Needs verification | I13: High | J13: Complete S5 before claiming implementability. | M13: Manuscript
A14: 9. Limitations and boundary conditions | B14: State where the framework may fail or require different variables. | C14: Transparent and scientifically protective. | D14: Could distinguish review limitations from framework limitations. | E14: Split into two short subgroups. | F14: 194 | G14: 4 | H14: Complete | I14: Medium | J14: Retain explicit failure conditions. | M14: Manuscript
A15: 10. Conclusions | B15: Answer the question and broaden to field significance. | C15: Returns to receiver exposure and transferable process. | D15: Avoid repeating all tools and digital-control outlook. | E15: Tight 3–4 paragraph conclusion. | F15: 224 | G15: 4 | H15: Complete | I15: Medium | J15: End with one decisive sentence. | M15: Manuscript
... A17: References | B17: Provide accurate, relevant and traceable support. | C17: Broad evidence base with 127 references. | D17: Full source-level claim audit and current-reference verification incomplete. | E17: Complete Reference Audit sheet. | F17: 0 | G17: 2 | H17: Needs verification | I17: Critical | J17: Verify every load-bearing claim and DOI. | M17: Manuscript

Sheet 04_Claim_Evidence
A1: Claim–Evidence Ledger
A2: Every load-bearing claim should have a source, an evidence type, a boundary, a qualifier where needed, and a verification decision.
A3: Claim ID | B3: Claim / sentence | C3: Claim class | D3: Importance | E3: Evidence type | F3: Supporting manuscript evidence | G3: Key references | H3: Support status | I3: Overclaim risk | J3: Corpus / scope boundary | K3: Required qualifier or revised wording | L3: Verification task | M3: Owner | N3: Status | O3: Priority | P3: Readiness score | Q3: Notes
A4: C01 | B4: The same frequency band can encode physically different food processes. | C4: Established physical principle | D4: Core | E4: Direct measurement | F4: Figure 1 / Table 1 taxonomy | G4: 1–13, 38, 48, 62–71 | H4: Supported | I4: Low | J4: Across technologies; not a universal dose comparison | K4: Retain; state that bands are typical and overlapping. | L4: Verify representative references for each modality. | N4: Needs verification | O4: High | P4: 3
A5: C02 | B5: Nominal frequency, dB, generator power and time do not uniquely define receiver exposure. | C5: Established + inference | D5: Core | E5: Direct measurement | F5: Equations / source-to-shelf chain | G5: 10–13, 62–70 | H5: Supported | I5: Low | J5: Route-specific; receiver variable differs by modality | K5: Retain. | L5: Check all equations and units. | N5: Needs verification | O5: High | P5: 3
A6: C03 | B6: Fruit is an evolving mechanical receiver whose transfer function changes with state. | C6: Supported inference | D6: Core | E6: Supported association | F6: Section 3.3; Figure 2 | G6: 14–25, 75–84 | H6: Supported | I6: Medium | J6: Mechanical characterization; not proof that actuation improves quality | K6: Use “changes with state” and avoid universal resonance claims. | L6: Verify commodity-specific evidence. | N6: Needs verification | O6: High | P6: 3
A7: C04 | B7: Modal features can track firmness or maturity in selected commodities. | C7: Established in bounded systems | D7: Supporting | E7: Direct measurement | F7: Sensing comparator section | G7: 14–25, 75–84 | H7: Supported | I7: Low | J7: Commodity- and geometry-specific | K7: Add “selected commodities and configurations.” | L7: Verify external validation and negative results. | N7: Needs verification | O7: Medium | P7: 3
A8: C05 | B8: Driving a measured fruit mode has not been shown to improve shelf quality. | C8: Absence / boundary claim | D8: Core | E8: Evidence-based inference | F8: Sensing-versus-actuation distinction | G8: 14–25, 75–84 | H8: Partial | I8: Medium | J8: Retained corpus and cited comparator literature | K8: Use “the reviewed evidence does not establish…” | L8: Search specifically for mode-targeted intervention studies. | N8: Needs verification | O8: Critical | P8: 2
A9: C06 | B9: Among seven retained airborne-fruit studies, none measured fruit motion. | C9: Corpus-bounded quantitative finding | D9: Core | E9: Direct extraction | F9: Table 2 / Figure 3 / S3 | G9: 26–30, 32–33 | H9: Partial | I9: High | J9: Only the retained corpus under the final protocol | K9: Use “none of the seven studies retained here…” | L9: Complete search, full-text verification and second-reviewer check. | N9: Needs verification | O9: Critical | P9: 2
A10: C07 | B10: Among seven retained studies, none isolated support-mediated transfer. | C10: Corpus-bounded quantitative finding | D10: Core | E10: Direct extraction | F10: Table 2 / Figure 3 / S3 | G10: 26–30, 32–33 | H10: Partial | I10: High | J10: Only the retained corpus | K10: Same corpus-bounded qualifier. | L10: Complete coding and source-page log. | N10: Needs verification | O10: Critical | P10: 2
A11: C08 | B11: Among seven retained studies, none externally validated exposure–quality transfer. | C11: Corpus-bounded quantitative finding | D11: Core | E11: Direct extraction | F11: Table 2 / Figure 3 / S3 | G11: 26–30, 32–33 | H11: Partial | I11: High | J11: Only the retained corpus | K11: Same corpus-bounded qualifier. | L11: Verify no external replication / transfer in full texts. | N11: Needs verification | O11: Critical | P11: 2
A12: C09 | B12: The detached-tomato papers form a connected evidence lineage rather than independent replication. | C12: Evidence-based inference | D12: Core | E12: Authorship / protocol comparison | F12: Section 4.1 | G12: 26–30 | H12: Supported | I12: Medium | J12: Connected investigators, material and treatment logic | K12: Use neutral wording; do not diminish observed outcomes. | L12: Check author and protocol overlap. | N12: Needs verification | O12: High | P12: 3
A13: C10 | B13: Different nominal dB values within the lineage do not reconstruct equivalent fruit exposure. | C13: Established physical principle applied to studies | D13: Supporting | E13: Direct extraction + inference | F13: Section 4.1 | G13: 28, 30 | H13: Supported | I13: Low | J13: 80 versus 100 dB are source-side labels | K13: Retain. | L13: Verify reported source levels and measurement locations. | N13: Needs verification | O13: High | P13: 3
A14: C11 | B14: Firmness alone cannot establish cell-wall preservation. | C14: Critical interpretation | D14: Supporting | E14: Comparative evidence | F14: Section 4.4 / contradiction matrix | G14: 58–61, 92–94 | H14: Supported | I14: Low | J14: Firmness integrates multiple structures and states | K14: Retain. | L14: Check that cited studies support contrasting mechanisms. | N14: Needs verification | O14: High | P14: 3
A15: C12 | B15: Mechanosensitive calcium/redox pathways are biologically plausible but unproven as the route in intact fruit. | C15: Hypothesis boundary | D15: Core | E15: Supported association | F15: Section 4.5 | G15: 85–90 | H15: Supported | I15: Low | J15: Cell / plant plausibility does not establish intact-fruit strain | K15: Retain conditional wording. | L15: Verify exact mechanistic scope of each source. | N15: Needs verification | O15: High | P15: 3
... A28: C25 | B28: The next breakthrough is closing the loaded-field → support → fruit-motion → tissue-exposure → shelf-response chain. | C28: Synthesis / position | D28: Core | E28: Evidence-based inference | F28: Conclusion | G28: Whole review | H28: Supported | I28: Low | J28: Scientific position, not empirical result | K28: Retain as final message. | L28: Ensure each link has a corresponding audit field. | N28: Complete | O28: High | P28: 4

Sheet 05_Study_Comparison
A1: Primary Airborne-Fruit Study Comparison
A2: Detailed comparison of research question, receiver, methods, measurements, findings, limitations and contribution. “Verify full text” fields must be completed from source papers.
A3: Study ID | B3: Full citation / DOI | C3: Receiver / context | D3: Research question | E3: Assumed mechanism / theory | F3: Reported source recipe | G3: Sample / experimental unit | H3: Treatment geometry / chamber | I3: Physical exposure measurements | J3: Environmental controls | K3: Biological / quality measurements | L3: Main reported finding | M3: Statistical / replication notes | N3: Agreement with lineage | O3: Disagreement / novelty | P3: Principal limitation | Q3: Contribution | R3: Independent replication? | S3: Full-text verified? | T3: Audit notes
A4: Kim et al. 2015 [26] Detached tomato | B4: Kim JY, Lee JS, Kwon TR, Lee SI, Kim JA, Lee GM, et al. (2015). Sound waves delay tomato fruit ripening by negatively regulating ethylene biosynthesis and signaling genes. Postharvest Biology and Technology, 110, 43-50. https://doi.org/10.1016/j.postharvbio.2015.07.015 | https://doi.org/10.1016/j.postharvbio.2015.07.015 | C4: Kim et al. 2015 [26] Detached tomato | D4: Can airborne sound delay ripening, implicitly through a sound-responsive physiological pathway? | E4: Mechanical / physiological pathway inferred from treatment label; verify exact author theory. | F4: 1 kHz; six-hour treatment; reported source level in original paper | G4: Verify full text: sample size, chamber/run unit and biological replicate structure. | H4: Verify full text: source distance, orientation, load, chamber dimensions and support. | I4: No fruit motion; no support isolation; nominal field only | J4: Verify temperature, humidity, airflow, gas history, shams and background vibration. | K4: Colour, firmness, ethylene / CO₂ trajectories and ripening-related gene expression | L4: Repeated phenotype and molecular association within one treatment system | M4: Verify randomization, nesting, repeated measures and correct experimental unit. | N4: Builds on / is adjacent to the connected tomato or plant evidence lineage. | O4: See manuscript Table 2 and Section 5 for divergence. | P4: Receiver motion, tray vibration, microclimate and chamber-level replication remain unresolved | Q4: Established the core detached-tomato observation and motivated later molecular work | R4: No external confirmation identified in retained corpus. | S4: No
A5: Kim et al. 2016 [27] Detached tomato | B5: Kim JY, Ahn HR, Kim ST, Min CW, Lee SI, Kim JA, et al. (2016). Sound wave affects the expression of ethylene biosynthesis-related genes through control of transcription factors RIN and HB-1. Plant Biotechnology Reports, 10(6), 437-445. https://doi.org/10.1007/s11816-016-0419-2 | https://doi.org/10.1007/s11816-016-0419-2 | C5: Kim et al. 2016 [27] Detached tomato | D5: Does sound alter ethylene-biosynthesis-related transcription through RIN and HB-1? | E5: Mechanical / physiological pathway inferred from treatment label; verify exact author theory. | F5: Related 1 kHz treatment lineage | G5: Verify full text: sample size, chamber/run unit and biological replicate structure. | H5: Verify full text: source distance, orientation, load, chamber dimensions and support. | I5: No fruit motion or route separation reported | J5: Verify temperature, humidity, airflow, gas history, shams and background vibration. | K5: Transcription factors and ethylene-biosynthesis-related genes | L5: Molecular association consistent with the earlier phenotype | M5: Verify randomization, nesting, repeated measures and correct experimental unit. | N5: Builds on / is adjacent to the connected tomato or plant evidence lineage. | O5: See manuscript Table 2 and Section 5 for divergence. | P5: Same lineage; physical exposure and alternative routes remain latent | Q5: Extended the proposed pathway to transcriptional control | R5: No external confirmation identified in retained corpus. | S5: No
A6: Kim et al. 2018 [28] Detached tomato | B6: Kim JY, Kim SK, Jung J, Jeong MJ, Ryu CM. (2018). Exploring the sound-modulated delay in tomato ripening through expression analysis of coding and non-coding RNAs. Annals of Botany. https://doi.org/10.1093/aob/mcy134 | https://doi.org/10.1093/aob/mcy134 | C6: Kim et al. 2018 [28] Detached tomato | D6: Which coding and non-coding RNAs accompany delayed ripening? | E6: Mechanical / physiological pathway inferred from treatment label; verify exact author theory. | F6: 1 kHz; nominal 80 dB reported | G6: Verify full text: sample size, chamber/run unit and biological replicate structure. | H6: Verify full text: source distance, orientation, load, chamber dimensions and support. | I6: No receiver motion or support isolation reported | J6: Verify temperature, humidity, airflow, gas history, shams and background vibration. | K6: Time-course expression of coding and non-coding RNAs | L6: Temporal molecular association under the treatment label | M6: Verify randomization, nesting, repeated measures and correct experimental unit. | N6: Builds on / is adjacent to the connected tomato or plant evidence lineage. | O6: See manuscript Table 2 and Section 5 for divergence. | P6: Nominal source level does not reconstruct fruit exposure; maturity alignment can confound interpretation | Q6: Broadened the molecular signature and temporal evidence | R6: No external confirmation identified in retained corpus. | S6: No
A7: Kim et al. 2023 [29] Detached tomato | B7: Kim JY, Lee HJ, Jeong MJ. (2023). Epigenetic regulation for delaying tomato fruit ripening through histone modification by specific sound wave treatment. Postharvest Biology and Technology, 197, 112211. https://doi.org/10.1016/j.postharvbio.2022.112211 | https://doi.org/10.1016/j.postharvbio.2022.112211 | C7: Kim et al. 2023 [29] Detached tomato | D7: Does sound exposure alter histone modification linked with ripening delay? | E7: Mechanical / physiological pathway inferred from treatment label; verify exact author theory. | F7: Related 1 kHz treatment lineage | G7: Verify full text: sample size, chamber/run unit and biological replicate structure. | H7: Verify full text: source distance, orientation, load, chamber dimensions and support. | I7: No discriminating mechanical control reported | J7: Verify temperature, humidity, airflow, gas history, shams and background vibration. | K7: Histone modification and ripening-related outcomes | L7: Epigenetic association within a bounded system | M7: Verify randomization, nesting, repeated measures and correct experimental unit. | N7: Builds on / is adjacent to the connected tomato or plant evidence lineage. | O7: See manuscript Table 2 and Section 5 for divergence. | P7: Receiver route and causal temporal sequence remain unclosed | Q7: Added an epigenetic layer to the connected evidence lineage | R7: No external confirmation identified in retained corpus. | S7: No
A8: Jeong et al. 2023 [30] Detached tomato | B8: Jeong MJ, Ko BJ, Kim JY. (2023). Mass spectrometry-based metabolomics study for delay tomato fruit ripening by sound waves. Journal of Analytical Science and Technology, 14(1), 27. https://doi.org/10.1186/s40543-023-00384-3 | https://doi.org/10.1186/s40543-023-00384-3 | C8: Jeong et al. 2023 [30] Detached tomato | D8: Which metabolites accompany delayed ripening under sound treatment? | E8: Mechanical / physiological pathway inferred from treatment label; verify exact author theory. | F8: 1 kHz; nominal 100 dB reported | G8: Verify full text: sample size, chamber/run unit and biological replicate structure. | H8: Verify full text: source distance, orientation, load, chamber dimensions and support. | I8: No fruit motion; limited environmental control described in review corpus | J8: Verify temperature, humidity, airflow, gas history, shams and background vibration. | K8: Selected metabolomic differences and ripening phenotype | L8: Association between treatment label and metabolite set | M8: Verify randomization, nesting, repeated measures and correct experimental unit. | N8: Builds on / is adjacent to the connected tomato or plant evidence lineage. | O8: See manuscript Table 2 and Section 5 for divergence. | P8: Different nominal level from related papers; selected sampling time may reflect maturity divergence | Q8: Added metabolomic evidence but not mechanical closure | R8: No external confirmation identified in retained corpus. | S8: No
A9: Ozkurt & Altuntas 2018 [32] Fruit on living strawberry plants | B9: Ozkurt H, Altuntas O. (2018). Quality Parameter Levels of Strawberry Fruit in Response to Different Sound Waves at 1000 Hz with Different dB Values (95, 100, 105 dB). Agronomy, 8(7), 127. https://doi.org/10.3390/agronomy8070127 | https://doi.org/10.3390/agronomy8070127 | C9: Ozkurt & Altuntas 2018 [32] Fruit on living strawberry plants | D9: Do different source levels at 1000 Hz affect fruit quality on plants? | E9: Mechanical / physiological pathway inferred from treatment label; verify exact author theory. | F9: 1000 Hz at 95, 100 and 105 dB | G9: Verify full text: sample size, chamber/run unit and biological replicate structure. | H9: Verify full text: source distance, orientation, load, chamber dimensions and support. | I9: No direct fruit motion or support-transfer measurement | J9: Verify temperature, humidity, airflow, gas history, shams and background vibration. | K9: Fruit quality parameters after repeated whole-plant exposure | L9: Bounded plant-level association with randomized block design | M9: Verify randomization, nesting, repeated measures and correct experimental unit. | N9: Builds on / is adjacent to the connected tomato or plant evidence lineage. | O9: See manuscript Table 2 and Section 5 for divergence. | P9: Receiver is the entire living plant, not a detached stored fruit; chronic exposure and chamber effects differ | Q9: Provides adjacent biological evidence, not validation of detached-fruit processing | R9: No external confirmation identified in retained corpus. | S9: No
A10: Altuntas & Ozkurt 2019 [33] Fruit on living tomato plants | B10: Altuntas O, Ozkurt H. (2019). The assessment of tomato fruit quality parameters under different sound waves. Journal of Food Science and Technology, 56(4), 2186-2194. https://doi.org/10.1007/s13197-019-03701-0 | https://doi.org/10.1007/s13197-019-03701-0 | C10: Altuntas & Ozkurt 2019 [33] Fruit on living tomato plants | D10: Do several sound frequencies alter tomato fruit quality during development? | E10: Mechanical / physiological pathway inferred from treatment label; verify exact author theory. | F10: 600, 1240 and 1600 Hz applied in successive weeks | G10: Verify full text: sample size, chamber/run unit and biological replicate structure. | H10: Verify full text: source distance, orientation, load, chamber dimensions and support. | I10: No direct fruit motion or route isolation | J10: Verify temperature, humidity, airflow, gas history, shams and background vibration. | K10: Fruit quality parameters under whole-plant exposure | L10: Exploratory association across development | M10: Verify randomization, nesting, repeated measures and correct experimental unit. | N10: Builds on / is adjacent to the connected tomato or plant evidence lineage. | O10: See manuscript Table 2 and Section 5 for divergence. | P10: Frequency is confounded with treatment order and developmental time | Q10: Shows why time, order and receiver identity must be separated | R10: No external confirmation identified in retained corpus. | S10: No

Sheet 06_Evidence_Chain
A1: Causal Evidence-Chain Audit
A2: A–D grades describe whether each specific causal link was established; they do not grade whether a reported outcome was statistically significant.
A4: Retained studies | D4: Receiver motion measured | G4: Support isolated | J4: External confirmation | M4: Total Grade-D cells
A5: 7 | D5: =COUNTIF(D8:D14,"A")+COUNTIF(D8:D14,"B") | G5: =COUNTIF(E8:E14,"A")+COUNTIF(E8:E14,"B") | J5: =COUNTIF(I8:I14,"A")+COUNTIF(I8:I14,"B") | M5: =COUNTIF(C8:I14,"D")
A7: Study | B7: Receiver system | C7: Loaded field | D7: Receiver motion | E7: Support isolated | F7: Thermal / gas sham | G7: Fruit-level unit | H7: Internal replication | I7: External confirmation | J7: Average grade | K7: Grade-D count | L7: Mechanistic closure | M7: Overall interpretation | N7: Source page / note | O7: Reviewer note
A8: Kim 2015 | B8: Detached tomato | C8: C | D8: D | E8: D | F8: C | G8: B | H8: B | I8: D | J8: =ROUND(AVERAGE(VLOOKUP(C8,Lists!$M$2:$N$5,2,FALSE),VLOOKUP(D8,Lists!$M$2:$N$5,2,FALSE),VLOOKUP(E8,Lists!$M$2:$N$5,2,FALSE),VLOOKUP(F8,Lists!$M$2:$N$5,2,FALSE),VLOOKUP(G8,Lists!$M$2:$N$5,2,FALSE),VLOOKUP(H8,Lists!$M$2:$N$5,2,FALSE),VLOOKUP(I8,Lists!$M$2:$N$5,2,FALSE)),2) | K8: =COUNTIF(C8:I8,"D") | L8: =IF(AND(D8<>"D",E8<>"D",I8<>"D"),"Partly closed","Open") | M8: Repeated outcome signal with latent mechanical exposure. | N8: Supplementary Table S3; verify exact source pages.
A9: Kim 2016 | B9: Detached tomato | C9: C | D9: D | E9: D | F9: C | G9: C | H9: B | I9: D | J9: =ROUND(AVERAGE(VLOOKUP(C9,Lists!$M$2:$N$5,2,FALSE),VLOOKUP(D9,Lists!$M$2:$N$5,2,FALSE),VLOOKUP(E9,Lists!$M$2:$N$5,2,FALSE),VLOOKUP(F9,Lists!$M$2:$N$5,2,FALSE),VLOOKUP(G9,Lists!$M$2:$N$5,2,FALSE),VLOOKUP(H9,Lists!$M$2:$N$5,2,FALSE),VLOOKUP(I9,Lists!$M$2:$N$5,2,FALSE)),2) | K9: =COUNTIF(C9:I9,"D") | L9: =IF(AND(D9<>"D",E9<>"D",I9<>"D"),"Partly closed","Open") | M9: Molecular association within the same treatment lineage. | N9: Supplementary Table S3; verify exact source pages.
A10: Kim 2018 | B10: Detached tomato | C10: C | D10: D | E10: D | F10: C | G10: B | H10: B | I10: D | J10: =ROUND(AVERAGE(VLOOKUP(C10,Lists!$M$2:$N$5,2,FALSE),VLOOKUP(D10,Lists!$M$2:$N$5,2,FALSE),VLOOKUP(E10,Lists!$M$2:$N$5,2,FALSE),VLOOKUP(F10,Lists!$M$2:$N$5,2,FALSE),VLOOKUP(G10,Lists!$M$2:$N$5,2,FALSE),VLOOKUP(H10,Lists!$M$2:$N$5,2,FALSE),VLOOKUP(I10,Lists!$M$2:$N$5,2,FALSE)),2) | K10: =COUNTIF(C10:I10,"D") | L10: =IF(AND(D10<>"D",E10<>"D",I10<>"D"),"Partly closed","Open") | M10: Transcriptomic time course without receiver closure. | N10: Supplementary Table S3; verify exact source pages.
A11: Kim 2023 | B11: Detached tomato | C11: C | D11: D | E11: D | F11: C | G11: C | H11: B | I11: D | J11: =ROUND(AVERAGE(VLOOKUP(C11,Lists!$M$2:$N$5,2,FALSE),VLOOKUP(D11,Lists!$M$2:$N$5,2,FALSE),VLOOKUP(E11,Lists!$M$2:$N$5,2,FALSE),VLOOKUP(F11,Lists!$M$2:$N$5,2,FALSE),VLOOKUP(G11,Lists!$M$2:$N$5,2,FALSE),VLOOKUP(H11,Lists!$M$2:$N$5,2,FALSE),VLOOKUP(I11,Lists!$M$2:$N$5,2,FALSE)),2) | K11: =COUNTIF(C11:I11,"D") | L11: =IF(AND(D11<>"D",E11<>"D",I11<>"D"),"Partly closed","Open") | M11: Epigenetic association without a discriminating mechanical control. | N11: Supplementary Table S3; verify exact source pages.
A12: Jeong 2023 | B12: Detached tomato | C12: C | D12: D | E12: D | F12: B | G12: C | H12: C | I12: D | J12: =ROUND(AVERAGE(VLOOKUP(C12,Lists!$M$2:$N$5,2,FALSE),VLOOKUP(D12,Lists!$M$2:$N$5,2,FALSE),VLOOKUP(E12,Lists!$M$2:$N$5,2,FALSE),VLOOKUP(F12,Lists!$M$2:$N$5,2,FALSE),VLOOKUP(G12,Lists!$M$2:$N$5,2,FALSE),VLOOKUP(H12,Lists!$M$2:$N$5,2,FALSE),VLOOKUP(I12,Lists!$M$2:$N$5,2,FALSE)),2) | K12: =COUNTIF(C12:I12,"D") | L12: =IF(AND(D12<>"D",E12<>"D",I12<>"D"),"Partly closed","Open") | M12: Selected metabolomic set and different nominal level. | N12: Supplementary Table S3; verify exact source pages.
A13: Ozkurt & Altuntas 2018 | B13: Fruit on living strawberry plants | C13: C | D13: D | E13: D | F13: C | G13: C | H13: B | I13: D | J13: =ROUND(AVERAGE(VLOOKUP(C13,Lists!$M$2:$N$5,2,FALSE),VLOOKUP(D13,Lists!$M$2:$N$5,2,FALSE),VLOOKUP(E13,Lists!$M$2:$N$5,2,FALSE),VLOOKUP(F13,Lists!$M$2:$N$5,2,FALSE),VLOOKUP(G13,Lists!$M$2:$N$5,2,FALSE),VLOOKUP(H13,Lists!$M$2:$N$5,2,FALSE),VLOOKUP(I13,Lists!$M$2:$N$5,2,FALSE)),2) | K13: =COUNTIF(C13:I13,"D") | L13: =IF(AND(D13<>"D",E13<>"D",I13<>"D"),"Partly closed","Open") | M13: Whole-plant exposure is adjacent evidence, not a detached-fruit process. | N13: Supplementary Table S3; verify exact source pages.
A14: Altuntas & Ozkurt 2019 | B14: Fruit on living tomato plants | C14: C | D14: D | E14: D | F14: C | G14: C | H14: C | I14: D | J14: =ROUND(AVERAGE(VLOOKUP(C14,Lists!$M$2:$N$5,2,FALSE),VLOOKUP(D14,Lists!$M$2:$N$5,2,FALSE),VLOOKUP(E14,Lists!$M$2:$N$5,2,FALSE),VLOOKUP(F14,Lists!$M$2:$N$5,2,FALSE),VLOOKUP(G14,Lists!$M$2:$N$5,2,FALSE),VLOOKUP(H14,Lists!$M$2:$N$5,2,FALSE),VLOOKUP(I14,Lists!$M$2:$N$5,2,FALSE)),2) | K14: =COUNTIF(C14:I14,"D") | L14: =IF(AND(D14<>"D",E14<>"D",I14<>"D"),"Partly closed","Open") | M14: Frequency is confounded with time and order. | N14: Supplementary Table S3; verify exact source pages.
A17: Domain summary
A18: Domain | B18: A count | C18: B count | D18: C count | E18: D count | F18: Mean grade | G18: Interpretive note
A19: Loaded field | B19: =COUNTIF(C$8:C$14,"A") | C19: =COUNTIF(C$8:C$14,"B") | D19: =COUNTIF(C$8:C$14,"C") | E19: =COUNTIF(C$8:C$14,"D") | F19: =ROUND(AVERAGE(VLOOKUP(C$8,Lists!$M$2:$N$5,2,FALSE),VLOOKUP(C$9,Lists!$M$2:$N$5,2,FALSE),VLOOKUP(C$10,Lists!$M$2:$N$5,2,FALSE),VLOOKUP(C$11,Lists!$M$2:$N$5,2,FALSE),VLOOKUP(C$12,Lists!$M$2:$N$5,2,FALSE),VLOOKUP(C$13,Lists!$M$2:$N$5,2,FALSE),VLOOKUP(C$14,Lists!$M$2:$N$5,2,FALSE)),2) | G19: Nominal / partial characterization dominates.
A20: Receiver motion | B20: =COUNTIF(D$8:D$14,"A") | C20: =COUNTIF(D$8:D$14,"B") | D20: =COUNTIF(D$8:D$14,"C") | E20: =COUNTIF(D$8:D$14,"D") | F20: =ROUND(AVERAGE(VLOOKUP(D$8,Lists!$M$2:$N$5,2,FALSE),VLOOKUP(D$9,Lists!$M$2:$N$5,2,FALSE),VLOOKUP(D$10,Lists!$M$2:$N$5,2,FALSE),VLOOKUP(D$11,Lists!$M$2:$N$5,2,FALSE),VLOOKUP(D$12,Lists!$M$2:$N$5,2,FALSE),VLOOKUP(D$13,Lists!$M$2:$N$5,2,FALSE),VLOOKUP(D$14,Lists!$M$2:$N$5,2,FALSE)),2) | G20: Principal physical link remains unmeasured.
A21: Support isolated | B21: =COUNTIF(E$8:E$14,"A") | C21: =COUNTIF(E$8:E$14,"B") | D21: =COUNTIF(E$8:E$14,"C") | E21: =COUNTIF(E$8:E$14,"D") | F21: =ROUND(AVERAGE(VLOOKUP(E$8,Lists!$M$2:$N$5,2,FALSE),VLOOKUP(E$9,Lists!$M$2:$N$5,2,FALSE),VLOOKUP(E$10,Lists!$M$2:$N$5,2,FALSE),VLOOKUP(E$11,Lists!$M$2:$N$5,2,FALSE),VLOOKUP(E$12,Lists!$M$2:$N$5,2,FALSE),VLOOKUP(E$13,Lists!$M$2:$N$5,2,FALSE),VLOOKUP(E$14,Lists!$M$2:$N$5,2,FALSE)),2) | G21: Airborne and structure-borne routes remain confounded.
A22: Thermal / gas sham | B22: =COUNTIF(F$8:F$14,"A") | C22: =COUNTIF(F$8:F$14,"B") | D22: =COUNTIF(F$8:F$14,"C") | E22: =COUNTIF(F$8:F$14,"D") | F22: =ROUND(AVERAGE(VLOOKUP(F$8,Lists!$M$2:$N$5,2,FALSE),VLOOKUP(F$9,Lists!$M$2:$N$5,2,FALSE),VLOOKUP(F$10,Lists!$M$2:$N$5,2,FALSE),VLOOKUP(F$11,Lists!$M$2:$N$5,2,FALSE),VLOOKUP(F$12,Lists!$M$2:$N$5,2,FALSE),VLOOKUP(F$13,Lists!$M$2:$N$5,2,FALSE),VLOOKUP(F$14,Lists!$M$2:$N$5,2,FALSE)),2) | G22: Controls vary; environmental routes remain plausible.
A23: Fruit-level unit | B23: =COUNTIF(G$8:G$14,"A") | C23: =COUNTIF(G$8:G$14,"B") | D23: =COUNTIF(G$8:G$14,"C") | E23: =COUNTIF(G$8:G$14,"D") | F23: =ROUND(AVERAGE(VLOOKUP(G$8,Lists!$M$2:$N$5,2,FALSE),VLOOKUP(G$9,Lists!$M$2:$N$5,2,FALSE),VLOOKUP(G$10,Lists!$M$2:$N$5,2,FALSE),VLOOKUP(G$11,Lists!$M$2:$N$5,2,FALSE),VLOOKUP(G$12,Lists!$M$2:$N$5,2,FALSE),VLOOKUP(G$13,Lists!$M$2:$N$5,2,FALSE),VLOOKUP(G$14,Lists!$M$2:$N$5,2,FALSE)),2) | G23: Outcome unit needs full-text verification in several studies.
A24: Internal replication | B24: =COUNTIF(H$8:H$14,"A") | C24: =COUNTIF(H$8:H$14,"B") | D24: =COUNTIF(H$8:H$14,"C") | E24: =COUNTIF(H$8:H$14,"D") | F24: =ROUND(AVERAGE(VLOOKUP(H$8,Lists!$M$2:$N$5,2,FALSE),VLOOKUP(H$9,Lists!$M$2:$N$5,2,FALSE),VLOOKUP(H$10,Lists!$M$2:$N$5,2,FALSE),VLOOKUP(H$11,Lists!$M$2:$N$5,2,FALSE),VLOOKUP(H$12,Lists!$M$2:$N$5,2,FALSE),VLOOKUP(H$13,Lists!$M$2:$N$5,2,FALSE),VLOOKUP(H$14,Lists!$M$2:$N$5,2,FALSE)),2) | G24: Bounded internal signals exist, but connected lineage limits independence.
A25: External confirmation | B25: =COUNTIF(I$8:I$14,"A") | C25: =COUNTIF(I$8:I$14,"B") | D25: =COUNTIF(I$8:I$14,"C") | E25: =COUNTIF(I$8:I$14,"D") | F25: =ROUND(AVERAGE(VLOOKUP(I$8,Lists!$M$2:$N$5,2,FALSE),VLOOKUP(I$9,Lists!$M$2:$N$5,2,FALSE),VLOOKUP(I$10,Lists!$M$2:$N$5,2,FALSE),VLOOKUP(I$11,Lists!$M$2:$N$5,2,FALSE),VLOOKUP(I$12,Lists!$M$2:$N$5,2,FALSE),VLOOKUP(I$13,Lists!$M$2:$N$5,2,FALSE),VLOOKUP(I$14,Lists!$M$2:$N$5,2,FALSE)),2) | G25: No external transfer identified in retained corpus.

Sheet 07_Contradictions
A1: Contradiction and Rival-Explanation Matrix
A2: Convert apparent disagreement into hidden variables, discriminating measurements, pass conditions and explicit failure interpretations.
A3: ID | B3: Apparent contradiction / claim | C3: Literature clusters | D3: Where evidence agrees | E3: Where evidence differs | F3: Hidden variable / rival explanation | G3: Measurement required | H3: Decisive experiment | I3: Result supporting receiver-centred interpretation | J3: Failure condition / next inference | K3: Evidence class | L3: Priority | M3: Status | N3: Owner | O3: Due date | P3: Notes
A4: X01 | B4: Airborne sound effect versus structure-borne treatment | C4: Airborne-fruit intervention + transport vibration | D4: Multiple routes can move fruit or alter chamber conditions. | E4: Studies attribute outcome to “sound” without route separation. | F4: Loudspeaker reaction force, tray motion, packaging contact or altered microclimate | G4: Pressure and particle velocity, triaxial shelf acceleration, fruit-surface velocity, temperature, airflow and gases | H4: Mechanically isolate the source; include support-only shaker and matched microclimate shams | I4: Outcome follows measured airborne fruit motion after support and environment are bounded | J4: Outcome follows tray acceleration or microclimate; reinterpret the route | K4: Evidence-based inference | L4: High | M4: In progress
A5: X02 | B5: “Fruit resonance” versus chamber, tray or local peel mode | C5: Tomato modal analysis + 1 kHz treatment lineage | D5: Fruit and chambers have frequency-dependent responses. | E5: Treatment uses 1 kHz while reported low-order fruit modes lie in tens of hertz. | F5: Loaded enclosure modes, higher-order fruit modes, local contact modes | G5: Frequency-response function, mode shape, chamber map and support acceleration | H5: Hold local pressure constant on and away from a measured fruit response feature | I5: Response scales with fruit motion rather than on-label frequency | J5: No motion-dependent response; resonance explanation weakens | K5: Evidence-based inference | L5: High | M5: In progress
A6: X03 | B6: Frequency-specific effect versus mechanically equivalent exposure | C6: Airborne-fruit intervention / physical metrology | D6: Source frequency changes receiver response unless amplitude is adjusted. | E6: Studies compare frequency at unequal receiver motion. | F6: Different amplitudes produce different receiver motion at each frequency | G6: Receiver motion or validated strain proxy with uncertainty | H6: Adjust amplitude so two frequencies produce matched receiver exposure | I6: Comparable longitudinal quality at matched exposure | J6: Persistent frequency effect indicates another mechanism or measurement variable | K6: Evidence-based inference | L6: High | M6: In progress
A7: X04 | B7: Total energy versus peak, rate or recovery dependence | C7: Ultrasound pulsed/continuous + fatigue/adaptation literature | D7: Waveform and exposure history can change outcome. | E7: Total energy is often used although peak/rate/recovery may dominate. | F7: Threshold activation, fatigue, crest factor, duty cycle or adaptation | G7: Peak strain, strain rate, cycle count, duty cycle and recovery response | H7: Match total work while varying peak, pulse structure and recovery | I7: Outcome follows the prespecified peak/rate/history variable | J7: No stable exposure–response relation; revise the predictor | K7: Evidence-based inference | L7: Medium | M7: In progress
A8: X05 | B8: Molecular pathway versus maturity marker | C8: Tomato omics + ripening physiology | D8: Molecular markers and maturity co-evolve over time. | E8: Downstream markers are interpreted as mediation without temporal closure. | F8: Sampling at different physiological stages; downstream association without mediation | G8: Motion, calcium/redox, hormone, transcription and quality on nested timescales | H8: Combine route measurement with state-aligned sampling and selective perturbation | I8: Temporal order and attenuation match the proposed chain | J8: Markers follow maturity or remain after pathway disruption | K8: Evidence-based inference | L8: Medium | M8: In progress
A9: X06 | B9: Cavitation effect versus heat or streaming | C9: Liquid power ultrasound / cavitation metrology | D9: Cavitation, streaming and heat co-occur in loaded baths. | E9: Nominal power is treated as cavitation exposure. | F9: Nominal watts, calorimetric heating and mass transfer confounded with bubble activity | G9: Calorimetry, cavitation metric, hydrophone map, dissolved gas and temperature | H9: Match bulk power and temperature while varying measured cavitation activity | I9: Outcome tracks cavitation rather than nominal power or heat | J9: Outcome tracks heat/streaming; do not label it cavitation | K9: Evidence-based inference | L9: Medium | M9: In progress
A10: X07 | B10: Laboratory result versus transferable process | C10: All intervention + scale-up literature | D10: Position, load, batch and equipment affect exposure. | E10: Internal findings are often assumed to transfer without locked estimators. | F10: Position, batch, load, equipment or laboratory dependence | G10: Persistent fruit identity, spatial exposure map, uncertainty and external calibration | H10: Lock the estimator and test a new batch, load, chamber and laboratory | I10: Exposure–quality prediction remains calibrated outside development data | J10: Performance degrades; define a narrower operating domain or missing variable | K10: Evidence-based inference | L10: High | M10: In progress

Sheet 08_Gaps_Innovations
A1: High-Value Research Gaps and Innovation Priorities
A2: Prioritize non-generic gaps by evidence, tractability, impact, falsifiability and industrial leverage.
A3: Gap ID | B3: Precise gap | C3: Explicit / inferred | D3: Evidence it exists | E3: Why it is ignored | F3: Hidden variable / leverage point | G3: Proposed experiment | H3: Key measurements | I3: Expected result | J3: Failure condition | K3: Impact if solved | L3: Feasibility (1–5) | M3: Novelty (1–5) | N3: Citation utility (1–5) | O3: Industrial value (1–5) | P3: Risk (1–5) | Q3: Priority score | R3: Priority | S3: Status | T3: Owner | U3: Time horizon | V3: Source | W3: Notes
A4: G01 | B4: Loaded chamber fields are not linked to fruit motion in the same identified fruit. | C4: Explicit | D4: 0/7 receiver-motion finding; source-to-shelf break. | E4: Requires synchronized acoustic and mechanical metrology under biological loading. | F4: Receiver motion at each product position. | G4: Map pressure/particle velocity/support acceleration and laser-vibrometry response for tagged fruit. | H4: Pa, m s⁻¹, m s⁻², FRF, uncertainty, position. | I4: Explains variance and identifies dominant route. | J4: Motion does not improve prediction over source settings. | K4: Causal closure; common basis for scale-up. | L4: 4 | M4: 5 | N4: 5 | O4: 5 | P4: 3 | Q4: =ROUND((L4*0.20+M4*0.20+N4*0.20+O4*0.25+(6-P4)*0.15)*20,1) | R4: Critical | S4: In progress | U4: 12–24 months | V4: Table 2 / Figure 3
A5: G02 | B5: Airborne and structure-borne routes are not experimentally separated. | C5: Explicit | D5: Support isolation graded D across retained corpus. | E5: Speaker reaction force and tray contact are easy to overlook. | F5: Gate-zero route identification. | G5: Mechanically isolate source; support-only shaker; matched microclimate shams. | H5: Tray acceleration, fruit motion, pressure field, airflow, temperature. | I5: Outcome follows one bounded route. | J5: Multiple uncontrolled routes remain inseparable. | K5: Prevents misclassification of treatment mechanism. | L5: 5 | M5: 5 | N5: 5 | O5: 5 | P5: 2 | Q5: =ROUND((L5*0.20+M5*0.20+N5*0.20+O5*0.25+(6-P5)*0.15)*20,1) | R5: Critical | S5: In progress | U5: 6–12 months | V5: Table 3 FP0
A6: G03 | B6: Receiver state is not used to interpret or control exposure. | C6: Explicit | D6: Fruit stiffness, damping, turgor and contact evolve during storage. | E6: Requires pretreatment sensing and hierarchical modelling. | F6: State-dependent transfer function H(f,x). | G6: Measure baseline mechanical state; map state×exposure interaction longitudinally. | H6: Mass, geometry, temperature, FRF, damping, maturity, response. | I6: State explains exposure heterogeneity and shifts operating window. | J6: No reproducible state dependence or poor transfer. | K6: Enables precision treatment and prevents over/undertreatment. | L6: 4 | M6: 4 | N6: 5 | O6: 5 | P6: 3 | Q6: =ROUND((L6*0.20+M6*0.20+N6*0.20+O6*0.25+(6-P6)*0.15)*20,1) | R6: High | S6: Not started | U6: 12–24 months | V6: Section 3.3
A7: G04 | B7: Surface motion is not validated as internal tissue strain. | C7: Explicit | D7: Vibrometry measures surface velocity; mechanotransduction requires local deformation. | E7: Inverse problem requires material properties, boundary conditions and calibration. | F7: Surface-to-tissue reconstruction with uncertainty. | G7: Combine LDV, imaging/tomography and destructive calibration subset with finite-element model. | H7: Surface field, internal displacement/strain, material parameters, model error. | I7: Validated strain proxy predicts biology better than surface motion alone. | J7: Model error remains too high or non-identifiable. | K7: Makes mechanotransduction claims testable. | L7: 3 | M7: 5 | N7: 5 | O7: 4 | P7: 4 | Q7: =ROUND((L7*0.20+M7*0.20+N7*0.20+O7*0.25+(6-P7)*0.15)*20,1) | R7: High | S7: Not started | U7: 18–36 months | V7: Section 3.3
A8: G05 | B8: No validated receiver-equivalence criterion transfers treatment across devices. | C8: Inferred | D8: Different systems may use different settings yet produce similar exposure. | E8: Requires equivalence margins and external validation rather than optimization alone. | F8: Distance between exposure distributions and shelf trajectories. | G8: Develop in Chamber A; retune Chamber B; lock estimator; test new batch/lab. | H8: Exposure distribution, uncertainty, trajectory distance, calibration. | I8: Matched exposure yields equivalent shelf trajectory. | J8: Quality diverges despite matched measured exposure. | K8: Defines device-independent process identity. | L8: 3 | M8: 5 | N8: 5 | O8: 5 | P8: 4 | Q8: =ROUND((L8*0.20+M8*0.20+N8*0.20+O8*0.25+(6-P8)*0.15)*20,1) | R8: Critical | S8: Not started | U8: 24–36 months | V8: Figure 4 / Section 6.3
A9: G06 | B9: Shelf claims rely on isolated endpoints instead of complete trajectories. | C9: Explicit | D9: Firmness, gases and metabolites depend on timing and physiological state. | E9: Longitudinal studies are resource intensive and require correct units. | F9: Trajectory alignment at equal time and equal physiological state. | G9: Track onset, peak, area, texture, colour, gases, mass loss, damage and sensory endpoints. | H9: Repeated measures and hierarchical trajectory model. | I9: Clarifies whether treatment delays, suppresses or redistributes response. | J9: Single endpoint remains inconsistent with trajectory. | K9: Converts laboratory outcomes into shelf decisions. | L9: 4 | M9: 4 | N9: 5 | O9: 5 | P9: 3 | Q9: =ROUND((L9*0.20+M9*0.20+N9*0.20+O9*0.25+(6-P9)*0.15)*20,1) | R9: High | S9: In progress | U9: 12–24 months | V9: Section 7.1
A10: G07 | B10: Experimental units and replication are often mismatched to exposure and outcome. | C10: Explicit | D10: Fruit, vessel and chamber can be different units. | E10: Many assays create technical replicates that look like biological replication. | F10: Correct hierarchical unitization. | G10: Design chamber/run, vessel and fruit replication with randomization across batch and position. | H10: Variance components, ICC, run/batch effects. | I10: Valid uncertainty and reproducible inference. | J10: Pseudoreplication dominates the result. | K10: Improves reliability across the field. | L10: 5 | M10: 4 | N10: 5 | O10: 4 | P10: 2 | Q10: =ROUND((L10*0.20+M10*0.20+N10*0.20+O10*0.25+(6-P10)*0.15)*20,1) | R10: Critical | S10: Not started | U10: 6–12 months | V10: Section 3.4 / S5
A11: G08 | B11: Every fruit cannot be instrumented in a dense chamber. | C11: Explicit | D11: Occlusion, contact and throughput prevent per-fruit measurement. | E11: Practical sensing architecture remains undeveloped. | F11: Sentinel fruit + batch-state distribution. | G11: Validate sentinel placement and estimator across loads, positions and batches. | H11: Sentinel response, batch state, prediction intervals, out-of-domain detection. | I11: Small sensor set predicts exposure distribution with calibrated uncertainty. | J11: Sentinels fail under load changes. | K11: Enables practical commissioning and control. | L11: 4 | M11: 5 | N11: 5 | O11: 5 | P11: 3 | Q11: =ROUND((L11*0.20+M11*0.20+N11*0.20+O11*0.25+(6-P11)*0.15)*20,1) | R11: High | S11: Not started | U11: 12–24 months | V11: Section 3.4 / Figure S2
A12: G09 | B12: Benefit and harm are not mapped in one state-specific operating window. | C12: Explicit | D12: Very low exposure may do nothing; higher exposure may cause stress or damage. | E12: Positive-result bias and lack of edge-of-failure experiments. | F12: State-specific no-effect, benefit and damage boundaries. | G12: Designed experiment spanning subthreshold to injury, including adverse outcomes. | H12: Exposure vector, quality, injury, temperature, noise, energy, throughput. | I12: Defines safe/useful region with uncertainty. | J12: No stable window or unacceptable process burden. | K12: Necessary for safety, regulation and industrial adoption. | L12: 3 | M12: 5 | N12: 5 | O12: 5 | P12: 4 | Q12: =ROUND((L12*0.20+M12*0.20+N12*0.20+O12*0.25+(6-P12)*0.15)*20,1) | R12: High | S12: Not started | U12: 18–36 months | V12: Section 6.2 / 7.2
A13: G10 | B13: No interoperable reporting/data standard links acoustic exposure to shelf response. | C13: Inferred | D13: Current studies cannot reconstruct treatment across laboratories. | E13: Variables differ by acoustic family and raw streams are large. | F13: Exposure Passport with family-specific modules. | G13: External lab attempts reconstruction from Passport and archived data. | H13: Completeness, reconstruction error, metadata quality, reproducibility. | I13: Independent lab reproduces exposure and analysis. | J13: Passport is too burdensome or insufficient. | K13: Creates a must-cite reporting reference and reusable data infrastructure. | L13: 4 | M13: 5 | N13: 5 | O13: 5 | P13: 3 | Q13: =ROUND((L13*0.20+M13*0.20+N13*0.20+O13*0.25+(6-P13)*0.15)*20,1) | R13: High | S13: In progress | U13: 12–24 months | V13: Section 6.1 / S4

Sheet 09_Figure_Audit
A1: Figure and Graphical-Abstract Audit
A2: Each visual must perform a unique scientific job, support a specific claim and remain readable at journal size.
A3: Figure ID | B3: Declarative title | C3: Scientific job | D3: Unique field contribution | E3: One-line message | F3: Claims supported | G3: Source data / verification required | H3: Evidence versus hypothesis coding clear? | I3: No duplication? | J3: Technical accuracy | K3: Readability at journal width | L3: Reusable / citation utility | M3: Caption self-contained? | N3: Editable source available? | O3: Current status | P3: Priority | Q3: Required revision | R3: Owner | S3: Notes
A4: GA | B4: Same sound setting, different treatments | C4: Communicate the whole paper in five seconds. | D4: Receiver exposure as the missing link from source to shelf. | E4: Measure what the fruit receives—not only what the machine emits. | F4: Core problem, 0/7 gap, Exposure Passport, Operating Window, transfer test. | G4: Verify 0/7 wording; keep only corpus-bounded callout. | H4: Partial | I4: Yes | J4: 3 | K4: 3 | L4: 4 | M4: Yes | N4: Yes | O4: Needs revision | P4: High | Q4: Reduce text; ensure the bottom message matches manuscript exactly.
A5: Fig 1 | B5: Frequency does not identify an acoustic food process | C5: Reclassify acoustic technologies by transfer path. | D5: Conceptual process-identity tuple and 25 kHz counterexample. | E5: One frequency label can hide multiple physical technologies. | F5: Contribution 1; Table 1. | G5: Verify typical ranges and all representative applications. | H5: Yes | I5: Yes | J5: 4 | K5: 3 | L5: 4 | M5: Yes | N5: Yes | O5: Complete | P5: High | Q5: Check minimum label size and grayscale accessibility.
A6: Fig 2 | B6: The fruit transforms a source setting into shelf performance | C6: Visualize the state-dependent source-to-shelf causal chain. | D6: Same source→different exposure; different source→matched exposure. | E6: The treatment changes when the receiver changes. | F6: Contribution 1 and central hypothesis. | G6: Ensure dashed vs solid arrows match evidence strength. | H6: Yes | I6: Yes | J6: 4 | K6: 3 | L6: 5 | M6: Yes | N6: Yes | O6: Needs revision | P6: Critical | Q6: Make receiver exposure the visual centre; simplify secondary labels.
A7: Fig 3 | B7: Current studies observe outcomes but do not close the causal bridge | C7: Make causal closure and contradictions auditable. | D7: Reusable causal-closure ladder plus evidence heatmap. | E7: Outcome evidence is not exposure evidence. | F7: Contribution 2; 0/7 findings; contradiction matrix. | G7: Second-reviewer audit and source-page log. | H7: Yes | I7: Yes | J7: 3 | K7: 3 | L7: 5 | M7: Yes | N7: Yes | O7: Needs verification | P7: Critical | Q7: Do not finalize until evidence coding is independently checked.
A8: Fig 4 | B8: Receiver-centred design converts an acoustic recipe into a transferable process | C8: Integrate reporting, operating window and external transfer. | D8: Links reconstructability, safe region and device-independent equivalence. | E8: Transfer the exposure and response—not the machine recipe. | F8: Contribution 3; decisive test. | G8: Equivalence notation, no invented margins, state-specific window. | H8: Yes | I8: Yes | J8: 3 | K8: 3 | L8: 5 | M8: Yes | N8: Yes | O8: Needs revision | P8: Critical | Q8: Use “proposed” and retain treat–retune–abstain logic.
A9: Fig S1 | B9: Question-led evidence synthesis and review boundary | C9: Document search, selection and evidence boundaries. | D9: Causal-chain critical-review workflow. | E9: Absence claims apply only to the retained corpus. | F9: Method reproducibility. | G9: Actual databases, dates, counts and exclusions. | H9: Yes | I9: Yes | J9: 3 | K9: 3 | L9: 4 | M9: Yes | N9: Yes | O9: Needs verification | P9: Critical | Q9: Populate only from final search log.
A10: Fig S2 | B10: Instrumentation and control architecture for closing the source-to-shelf chain | C10: Give laboratories an implementation blueprint. | D10: Loaded mapping + route isolation + sentinels + external validation. | E10: Measure the loaded system and separate rival pathways. | F10: Decisive experiments / industrial design. | G10: Instrument placement, calibration, uncertainty and unitization. | H10: Yes | I10: Yes | J10: 3 | K10: 3 | L10: 5 | M10: Yes | N10: Yes | O10: Needs revision | P10: High | Q10: Ensure controls look factorial and unvalidated closed loop remains dashed.

Sheet 10_Table_Audit
A1: Main and Supplementary Table Audit
A2: Tables should carry structured evidence or implementation detail that cannot be communicated more clearly in prose or figures.
A3: Table ID | B3: Title / role | C3: Scientific job | D3: Unique contribution | E3: Required fields | F3: Current completeness | G3: Source verification | H3: No duplication? | I3: Readable / usable? | J3: Status | K3: Priority | L3: Missing data / action | M3: Owner | N3: Due date | O3: Main or supplement | P3: Source file | Q3: Notes | R3: Readiness score
A4: Table 1 | B4: Acoustic technology families and defining variables | C4: Classify by band, route, mechanism, receiver variable and shelf objective. | D4: Mechanism-based taxonomy beyond frequency. | E4: Six modalities; typical band; path; mechanism; receiver variable; objective; confounder. | F4: Strong | G4: Needs source check | H4: Yes | I4: Yes | J4: Needs verification | K4: High | L4: Verify ranges and maturity wording; avoid universal deployment judgements. | O4: Main | P4: From_Sound_to_Shelf_TIFS_Critical_Review_Rewritten.docx | R4: 3
A5: Table 2 | B5: Critical comparison of seven airborne-fruit studies | C5: Compare questions, methods, physical measurements, outcomes, limits and contribution. | D5: Prevents narrative paper-by-paper summary. | E5: Full-text verified treatment, sample/unit, controls, measures, findings and limitations. | F5: Partial | G5: Incomplete | H5: Yes | I5: Yes | J5: Needs verification | K5: Critical | L5: Complete full-text extraction and sample/unit fields. | O5: Main | P5: From_Sound_to_Shelf_TIFS_Critical_Review_Rewritten.docx | R5: 2
A6: Table 3 | B6: Contradictions, hidden variables and decisive tests | C6: Translate disagreement into falsifiable experiments. | D6: Reusable contradiction-to-decision framework. | E6: Contradiction; hidden variable; measurement; experiment; support result; failure result. | F6: Strong | G6: Needs claim audit | H6: Yes | I6: Yes | J6: Needs verification | K6: High | L6: Verify every contradiction against cited sources. | O6: Main | P6: From_Sound_to_Shelf_TIFS_Critical_Review_Rewritten.docx | R6: 3
A7: Table S1 | B7: Search strategy, eligibility and documentation | C7: Make the review corpus reproducible. | D7: Search + boundary + exclusion record in one table. | E7: Databases; strings; dates; counts; exclusions; reviewer procedure. | F7: Incomplete | G7: Incomplete | H7: Yes | I7: Yes | J7: Not started | K7: Critical | L7: Populate from actual search and screening log. | O7: Supplement | P7: From_Sound_to_Shelf_TIFS_Supplementary_Material.docx | R7: 1
A8: Table S2 | B8: Complete study-extraction matrix | C8: Archive full study details beyond main Table 2. | D8: Auditable extraction with “not reported” rather than inference. | E8: Sample/unit, geometry, settings, controls, measurements, findings, limitations. | F8: Partial | G8: Incomplete | H8: Yes | I8: Yes | J8: Needs verification | K8: Critical | L8: Verify source pages and complete sample/geometry fields. | O8: Supplement | P8: From_Sound_to_Shelf_TIFS_Supplementary_Material.docx | R8: 2
A9: Table S3 | B9: Cell-level evidence-chain justification | C9: Make every A–D grade reproducible. | D9: Source-page evidence for each grade. | E9: Study, domain, grade, source location, rationale, second-reviewer decision. | F9: Partial | G9: Incomplete | H9: Yes | I9: Yes | J9: Needs verification | K9: Critical | L9: Add cell-by-cell source pages and agreement record. | O9: Supplement | P9: From_Sound_to_Shelf_TIFS_Supplementary_Material.docx | R9: 2
A10: Table S4 | B10: Exposure Passport data dictionary | C10: Define fields, units, uncertainty and modality applicability. | D10: Potential reporting standard / reusable implementation tool. | E10: Minimum tier, mechanistic tier, units, calibration, applicability. | F10: Strong | G10: Needs pilot | H10: Yes | I10: Yes | J10: Needs revision | K10: High | L10: Label as proposed; test reconstruction burden with an external lab. | O10: Supplement | P10: From_Sound_to_Shelf_TIFS_Supplementary_Material.docx | R10: 3
A11: Table S5 | B11: Decisive experiment and statistical validation plan | C11: Turn the framework into an implementable protocol. | D11: Links route controls, unitization, motion clamp, equivalence and external validation. | E11: Primary metric, units, sample-size basis, margin, model, pass/fail, data release. | F11: Partial | G11: Incomplete | H11: Yes | I11: Yes | J11: Needs verification | K11: Critical | L11: Add pilot-derived variance, sample size and equivalence margin. | O11: Supplement | P11: From_Sound_to_Shelf_TIFS_Supplementary_Material.docx | R11: 2

Sheet 11_Supplement_Audit
A1: Supplementary Material Audit
A2: The supplement should prove that the review, evidence coding and decisive experiment are reproducible—without duplicating the main paper.
A3: Item | B3: Purpose | C3: Must contain | D3: Current state | E3: Blocking fields | F3: Duplicates main paper? | G3: Author input required? | H3: Verification evidence | I3: Status | J3: Priority | K3: Action | L3: Owner | M3: Due date | N3: File / location | O3: Notes | P3: Readiness score
A4: Figure S1 | B4: Search and evidence workflow | C4: Databases, strings, dates, counts, inclusion/exclusion and review boundary. | D4: Template available. | E4: Actual search log and counts. | F4: No | G4: Yes | H4: Search export + exclusion log. | I4: Not started | J4: Critical | K4: Populate only with verified records. | N4: From_Sound_to_Shelf_TIFS_Supplementary_Material.docx | P4: 1
A5: Figure S2 | B5: Measurement and validation architecture | C5: Loaded map, route controls, sentinel fruit, external transfer. | D5: Draft available. | E5: Final instrument list, calibration and statistical unitization. | F5: No | G5: Partial | H5: Engineering and methods review. | I5: Needs revision | J5: High | K5: Simplify and align with Table S5. | N5: From_Sound_to_Shelf_TIFS_Supplementary_Material.docx | P5: 3
A6: Table S1 | B6: Search strategy / eligibility | C6: Exact strings, dates, counts and exclusions. | D6: Partially populated. | E6: All final databases and records. | F6: No | G6: Yes | H6: Search log. | I6: Not started | J6: Critical | K6: Finish before any exhaustive-sounding claim. | N6: From_Sound_to_Shelf_TIFS_Supplementary_Material.docx | P6: 1
A7: Table S2 | B7: Full study extraction | C7: Complete source-grounded record for seven studies. | D7: Partially populated. | E7: Sample sizes, geometry, controls, source pages. | F7: No | G7: Yes | H7: Full texts. | I7: Needs verification | J7: Critical | K7: Complete without inference. | N7: From_Sound_to_Shelf_TIFS_Supplementary_Material.docx | P7: 2
A8: Table S3 | B8: Grade justifications | C8: Each evidence grade linked to source location and rationale. | D8: Grade matrix populated; source pages absent. | E8: Cell-by-cell source pages and reviewer agreement. | F8: No | G8: Yes | H8: Coding log. | I8: Needs verification | J8: Critical | K8: Independent verification required. | N8: From_Sound_to_Shelf_TIFS_Supplementary_Material.docx | P8: 2
A9: Table S4 | B9: Exposure Passport dictionary | C9: Variables, units, methods, uncertainty and applicability. | D9: Strong proposed structure. | E9: External usability / burden test. | F9: No | G9: Partial | H9: Pilot reconstruction exercise. | I9: Needs revision | J9: High | K9: Label as proposed and test. | N9: From_Sound_to_Shelf_TIFS_Supplementary_Material.docx | P9: 3
A10: Table S5 | B10: Experiment / statistics plan | C10: Units, controls, motion clamp, sample size, equivalence and external validation. | D10: Design logic present. | E10: Pilot variance, sample size, equivalence margin and repository plan. | F10: No | G10: Yes | H10: Pilot / statistician sign-off. | I10: Not started | J10: Critical | K10: Complete before calling design implementable. | N10: From_Sound_to_Shelf_TIFS_Supplementary_Material.docx | P10: 1

Sheet 12_Reference_Audit
A1: Reference and Source Verification Audit
A2: 127 references extracted from the current manuscript. Verification fields are intentionally blank / pending.
A3: Ref # | B3: Full citation | C3: Year | D3: Journal / source | E3: DOI / URL | F3: Evidence cluster | G3: Source type | H3: Current / recent? | I3: Full text obtained? | J3: Citation details verified? | K3: Claim support checked? | L3: Data extracted? | M3: Primary claim(s) supported | N3: Duplicate DOI? | O3: Risk / issue | P3: Priority | Q3: Status
A4: 1 | B4: Soria AC, Villamiel M. (2010). Effect of ultrasound on the technological properties and bioactivity of food: a review. Trends in Food Science & Technology, 21(7), 323-331. https://doi.org/10.1016/j.tifs.2010.04.003 | C4: 2010 | D4: Effect of ultrasound on the technological properties and bioactivity of food: a review | E4: https://doi.org/10.1016/j.tifs.2010.04.003 | F4: Ultrasound reviews / mechanisms / scale-up | G4: Review | H4: No | I4: No | J4: No | K4: No | L4: No | N4: =IF(E4="","",IF(COUNTIF($E$4:$E$130,E4)>1,"Duplicate","")) | P4: Medium | Q4: Needs verification
A5: 2 | B5: Chemat F, Zill-e-Huma, Khan MK. (2011). Applications of ultrasound in food technology: Processing, preservation and extraction. Ultrasonics Sonochemistry, 18(4), 813-835. https://doi.org/10.1016/j.ultsonch.2010.11.023 | C5: 2011 | D5: Applications of ultrasound in food technology: Processing | E5: https://doi.org/10.1016/j.ultsonch.2010.11.023 | F5: Ultrasound reviews / mechanisms / scale-up | G5: Primary / research article | H5: No | I5: No | J5: No | K5: No | L5: No | N5: =IF(E5="","",IF(COUNTIF($E$4:$E$130,E5)>1,"Duplicate","")) | P5: Medium | Q5: Needs verification
A6: 3 | B6: Nicolau-Lapeña I, Lafarga T, Viñas I, Abadias M, Bobo G, Aguiló-Aguayo I. (2019). Ultrasound Processing Alone or in Combination with Other Chemical or Physical Treatments as a Safety and Quality Preservation Strategy of Fresh and Processed Fruits and Vegetables: A Review. Food and Bioprocess Technology, 12(9), 1452-1471. https://doi.org/10.1007/s11947-019-02313-y | C6: 2019 | D6: Ultrasound Processing Alone or in Combination with Other Chemical or Physical Treatments as a Safety and Quality Preservation Strategy of Fresh and Processed Fruits and Vegetables: A Review | E6: https://doi.org/10.1007/s11947-019-02313-y | F6: Ultrasound reviews / mechanisms / scale-up | G6: Review | H6: No | I6: No | J6: No | K6: No | L6: No | N6: =IF(E6="","",IF(COUNTIF($E$4:$E$130,E6)>1,"Duplicate","")) | P6: Medium | Q6: Needs verification
A7: 4 | B7: Lepaus BM, Valiati BS, Machado BG, Domingos MM, Silva MN, Faria-Silva L, et al. (2023). Impact of ultrasound processing on the nutritional components of fruit and vegetable juices. Trends in Food Science & Technology, 138, 752-765. https://doi.org/10.1016/j.tifs.2023.07.002 | C7: 2023 | D7: Impact of ultrasound processing on the nutritional components of fruit and vegetable juices | E7: https://doi.org/10.1016/j.tifs.2023.07.002 | F7: Ultrasound reviews / mechanisms / scale-up | G7: Primary / research article | H7: No | I7: No | J7: No | K7: No | L7: No | N7: =IF(E7="","",IF(COUNTIF($E$4:$E$130,E7)>1,"Duplicate","")) | P7: Medium | Q7: Needs verification
A8: 5 | B8: Guo M, Lv X, Wang D, Chen H, Wei F. (2025). Innovative integration of computer vision, IoT, and digital twin in food quality and safety assessment. Trends in Food Science & Technology, 163, 105176. https://doi.org/10.1016/j.tifs.2025.105176 | C8: 2025 | D8: Innovative integration of computer vision | E8: https://doi.org/10.1016/j.tifs.2025.105176 | F8: Ultrasound reviews / mechanisms / scale-up | G8: Primary / research article | H8: Yes | I8: No | J8: No | K8: No | L8: No | N8: =IF(E8="","",IF(COUNTIF($E$4:$E$130,E8)>1,"Duplicate","")) | P8: Medium | Q8: Needs verification
A9: 6 | B9: İnanlar B, Altay F. (2026). Digital twin technology in AI-operated metaverse for food processing: A pathway to sustainability, efficiency and innovation. Trends in Food Science & Technology, 168, 105491. https://doi.org/10.1016/j.tifs.2025.105491 | C9: 2026 | D9: Digital twin technology in AI-operated metaverse for food processing: A pathway to sustainability | E9: https://doi.org/10.1016/j.tifs.2025.105491 | F9: Ultrasound reviews / mechanisms / scale-up | G9: Primary / research article | H9: Yes | I9: No | J9: No | K9: No | L9: No | N9: =IF(E9="","",IF(COUNTIF($E$4:$E$130,E9)>1,"Duplicate","")) | P9: Medium | Q9: Needs verification
A10: 7 | B10: Li F, Qin Z, Ren C, Li W, Gao P, Zou X, et al. (2026). Multimodal nondestructive sensing and digital-twin-enabled quality control in soybean foods: A process-state-oriented review. Trends in Food Science & Technology, 174, 105815. https://doi.org/10.1016/j.tifs.2026.105815 | C10: 2026 | D10: Multimodal nondestructive sensing and digital-twin-enabled quality control in soybean foods: A process-state-oriented review | E10: https://doi.org/10.1016/j.tifs.2026.105815 | F10: Ultrasound reviews / mechanisms / scale-up | G10: Review | H10: Yes | I10: No | J10: No | K10: No | L10: No | N10: =IF(E10="","",IF(COUNTIF($E$4:$E$130,E10)>1,"Duplicate","")) | P10: Medium | Q10: Needs verification
A11: 8 | B11: Kumar G, Le DT, Durco J, Cianciosi S, Devkota L, Dhital S. (2023). Innovations in legume processing: Ultrasound-based strategies for enhanced legume hydration and processing. Trends in Food Science & Technology, 139, 104122. https://doi.org/10.1016/j.tifs.2023.104122 | C11: 2023 | D11: Innovations in legume processing: Ultrasound-based strategies for enhanced legume hydration and processing | E11: https://doi.org/10.1016/j.tifs.2023.104122 | F11: Ultrasound reviews / mechanisms / scale-up | G11: Primary / research article | H11: No | I11: No | J11: No | K11: No | L11: No | N11: =IF(E11="","",IF(COUNTIF($E$4:$E$130,E11)>1,"Duplicate","")) | P11: Medium | Q11: Needs verification
A12: 9 | B12: Zheng X, Zou B, Zhang J, Cai W, Na X, Du M, et al. (2024). Recent advances of ultrasound-assisted technology on aquatic protein processing: Extraction, modification, and freezing/thawing-induced oxidation. Trends in Food Science & Technology, 144, 104309. https://doi.org/10.1016/j.tifs.2023.104309 | C12: 2024 | D12: Recent advances of ultrasound-assisted technology on aquatic protein processing: Extraction | E12: https://doi.org/10.1016/j.tifs.2023.104309 | F12: Ultrasound reviews / mechanisms / scale-up | G12: Review | H12: Yes | I12: No | J12: No | K12: No | L12: No | N12: =IF(E12="","",IF(COUNTIF($E$4:$E$130,E12)>1,"Duplicate","")) | P12: Medium | Q12: Needs verification
A13: 10 | B13: Ashokkumar M. (2011). The characterization of acoustic cavitation bubbles – An overview. Ultrasonics Sonochemistry, 18(4), 864-872. https://doi.org/10.1016/j.ultsonch.2010.11.016 | C13: 2011 | D13: The characterization of acoustic cavitation bubbles – An overview | E13: https://doi.org/10.1016/j.ultsonch.2010.11.016 | F13: Ultrasound reviews / mechanisms / scale-up | G13: Primary / research article | H13: No | I13: No | J13: No | K13: No | L13: No | N13: =IF(E13="","",IF(COUNTIF($E$4:$E$130,E13)>1,"Duplicate","")) | P13: Medium | Q13: Needs verification
A14: 11 | B14: Kentish S, Feng H. (2014). Applications of Power Ultrasound in Food Processing. Annual Review of Food Science and Technology, 5(1), 263-284. https://doi.org/10.1146/annurev-food-030212-182537 | C14: 2014 | D14: Applications of Power Ultrasound in Food Processing | E14: https://doi.org/10.1146/annurev-food-030212-182537 | F14: Ultrasound reviews / mechanisms / scale-up | G14: Review | H14: No | I14: No | J14: No | K14: No | L14: No | N14: =IF(E14="","",IF(COUNTIF($E$4:$E$130,E14)>1,"Duplicate","")) | P14: Medium | Q14: Needs verification
A15: 12 | B15: Leong T, Juliano P, Knoerzer K. (2017). Advances in Ultrasonic and Megasonic Processing of Foods. Food Engineering Reviews, 9(3), 237-256. https://doi.org/10.1007/s12393-017-9167-5 | C15: 2017 | D15: Advances in Ultrasonic and Megasonic Processing of Foods | E15: https://doi.org/10.1007/s12393-017-9167-5 | F15: Ultrasound reviews / mechanisms / scale-up | G15: Review | H15: No | I15: No | J15: No | K15: No | L15: No | N15: =IF(E15="","",IF(COUNTIF($E$4:$E$130,E15)>1,"Duplicate","")) | P15: Medium | Q15: Needs verification
... A128: 125 | B128: Brilhante São José JF, Dantas Vanetti MC. (2012). Effect of ultrasound and commercial sanitizers in removing natural contaminants and Salmonella enterica Typhimurium on cherry tomatoes. Food Control, 24(1-2), 95-99. https://doi.org/10.1016/j.foodcont.2011.09.008 | C128: 2012 | D128: Effect of ultrasound and commercial sanitizers in removing natural contaminants and Salmonella enterica Typhimurium on cherry tomatoes | E128: https://doi.org/10.1016/j.foodcont.2011.09.008 | F128: Ultrasound + sanitizer studies | G128: Primary / research article | H128: No | I128: No | J128: No | K128: No | L128: No | N128: =IF(E128="","",IF(COUNTIF($E$4:$E$130,E128)>1,"Duplicate","")) | P128: Medium | Q128: Needs verification
A129: 126 | B129: Aweta. Technology and software: AFS Sense firmness assessment technology. Available at: https://www.aweta.com/technology/ (accessed 15 September 2026). | D129: Available at: https://www.aweta.com/technology/ (accessed 15 September 2026). | E129: https://www.aweta.com/technology/ | F129: Commercial vendor evidence | G129: Vendor webpage | H129: No | I129: No | J129: No | K129: No | L129: No | N129: =IF(E129="","",IF(COUNTIF($E$4:$E$130,E129)>1,"Duplicate","")) | P129: High | Q129: Needs verification
A130: 127 | B130: International Council for Harmonisation. ICH Harmonised Guideline Q8(R2): Pharmaceutical Development. August 2009. Available at: https://database.ich.org/sites/default/files/Q8_R2_Guideline.pdf (accessed 15 September 2026). | D130: August 2009 | E130: https://database.ich.org/sites/default/files/Q8_R2_Guideline.pdf | F130: Design-space guideline / analogy | G130: Guideline / standard | H130: No | I130: No | J130: No | K130: No | L130: No | N130: =IF(E130="","",IF(COUNTIF($E$4:$E$130,E130)>1,"Duplicate","")) | P130: High | Q130: Needs verification

Sheet 13_TIFS_Compliance
A1: TIFS Submission and Package Compliance Audit
A2: Numeric article-type limits must be checked against the live Guide for Authors / Editorial Manager. Unverified AI-generated limits are not treated as official.
A3: ID | B3: Requirement / check | C3: Current manuscript state | D3: Target / rule | E3: Verification source | F3: Compliant? | G3: Status | H3: Priority | I3: Required action | J3: Owner | K3: Due date | L3: Notes
A4: J01 | B4: Article type | C4: Critical review and research agenda. | D4: Confirm accepted article type and invitation requirements, if any. | E4: Live TIFS Guide for Authors / Editorial Manager | F4: Partial | G4: Needs verification | H4: Critical | I4: Verify current article-type policy.
A5: J02 | B5: Title | C5: From Sound to Shelf: Mechanisms, Evidence, and Receiver-Centred Process Design for Acoustic Processing of Intact Fruit | D5: Concise, searchable and scope-accurate. | E5: Editorial judgement | F5: Yes | G5: Complete | H5: High | I5: Keep receiver-centred novelty visible.
A6: J03 | B6: Abstract word count | C6: 244 | D6: Check current TIFS limit. | E6: Live Guide for Authors | F6: =IF(C6<=250,"Yes","Partial") | G6: Needs verification | H6: High | I6: Confirm current limit and final count.
A7: J04 | B7: Main text word count | C7: 5475 | D7: Check current review limit and what is excluded. | E7: Live Guide for Authors | F7: Partial | G7: Needs verification | H7: High | I7: Confirm official counting method.
A8: J05 | B8: Highlights | C8: 5 highlights present. | D8: Confirm number and character limit. | E8: Live Guide for Authors | F8: Partial | G8: Needs verification | H8: Medium | I8: Check formatting and character count.
A9: J06 | B9: Graphical abstract | C9: 1 separate graphical abstract. | D9: Confirm size and upload category. | E9: Submission portal | F9: Partial | G9: Needs verification | H9: Medium | I9: Verify dimensions, font size and file type.
A10: J07 | B10: Main visual count | C10: 4 figures + 3 tables = 7 total. | D10: Conservative structure; verify current official limit. | E10: Live Guide for Authors | F10: Partial | G10: Needs verification | H10: High | I10: Do not rely on unverified AI Mode limits.
A11: J08 | B11: Supplementary visual count | C11: 2 figures + 5 tables = 7 items. | D11: No duplication; all support reproducibility. | E11: Editorial judgement | F11: Yes | G11: In progress | H11: Medium | I11: Complete missing fields and verify file format.
A12: J09 | B12: Sequential citations | C12: Figures and tables cited sequentially in draft. | D12: Every item cited in order and captioned. | E12: Manuscript audit | F12: Partial | G12: Needs verification | H12: High | I12: Run final cross-reference audit after revisions.
A13: J10 | B13: Figure captions | C13: Separate legends file available. | D13: Self-contained, concise, defines abbreviations and evidence status. | E13: Guide for Authors | F13: Partial | G13: Needs revision | H13: High | I13: Final caption audit after figure redesign.
A14: J11 | B14: Figure file quality | C14: Editable SVG/PNG package exists. | D14: Check resolution, color mode and font embedding. | E14: Artwork guidelines | F14: Partial | G14: Needs verification | H14: High | I14: Export final TIFF/EPS/PDF as required.
A15: J12 | B15: Table titles / footnotes | C15: Titles and grade keys present. | D15: Self-contained; abbreviations and “not reported” rules clear. | E15: Guide for Authors | F15: Partial | G15: Needs revision | H15: Medium | I15: Add footnotes and source boundary consistently.
A16: J13 | B16: Review-method reproducibility | C16: Question-led method described; search records incomplete. | D16: Databases, strings, counts, exclusions, reviewer procedure. | E16: Supplement S1–S3 | F16: No | G16: Not started | H16: Critical | I16: Complete before submission.
A17: J14 | B17: Reference style | C17: 127 numbered references in draft. | D17: Verify journal style, DOI format and completeness. | E17: Live Guide / reference manager | F17: Partial | G17: Needs verification | H17: High | I17: Complete Reference Audit.
A18: J15 | B18: Permissions | C18: Figures are original; adapted concepts require careful attribution. | D18: Permissions for reused/adapted copyrighted material. | E18: Elsevier permissions policy | F18: Partial | G18: Needs verification | H18: High | I18: Document originality and permissions.
A19: J16 | B19: Author details | C19: Placeholders remain. | D19: Final author names, affiliations, ORCID and correspondence. | E19: Author input | F19: No | G19: Not started | H19: Critical | I19: Complete and lock before submission.
... A25: J22 | B25: Language / readability | C25: Active, concise style applied; detailed sentence audit included. | D25: Final professional proofread. | E25: Writing audit | F25: Partial | G25: In progress | H25: Medium | I25: Resolve long sentences and consistency.

Sheet 15_Writing_Sentences
A1: Sentence-Level Scientific Writing Audit
A2: Heuristic audit for sentence length, passive constructions, nominalizations and clutter. Human review remains essential.
A3: Section | B3: Paragraph # | C3: Sentence # | D3: Sentence | E3: Word count | F3: >25 words? | G3: Passive heuristic? | H3: Nominalization count | I3: Clutter phrase(s) | J3: Recommended action | K3: Reviewer status | L3: Reviewer note
A4: Subtitle | B4: 3 | C4: 1 | D4: Author One¹* · Author Two² · Author Three¹ | E4: 6 | F4: No | G4: No | H4: 0 | K4: Not reviewed
A5: Subtitle | B5: 4 | C5: 1 | D5: ¹ Affiliation to be completed ² Affiliation to be completed * Corresponding author email to be completed | E5: 16 | F5: No | G5: Yes | H5: 2 | J5: Consider active voice | K5: Not reviewed
A6: Highlights | B6: 6 | C6: 1 | D6: One acoustic frequency can encode several physically different food processes. | E6: 10 | F6: No | G6: No | H6: 1 | K6: Not reviewed
A7: Highlights | B7: 7 | C7: 1 | D7: Source settings do not define the exposure received by intact fruit. | E7: 11 | F7: No | G7: No | H7: 0 | K7: Not reviewed
A8: Highlights | B8: 8 | C8: 1 | D8: None of seven retained airborne-fruit studies measured fruit motion or isolated support transfer. | E8: 13 | F8: No | G8: No | H8: 1 | K8: Not reviewed
A9: Highlights | B9: 9 | C9: 1 | D9: Receiver-centred metrology converts apparent contradictions into falsifiable tests. | E9: 8 | F9: No | G9: No | H9: 0 | K9: Not reviewed
A10: Highlights | B10: 10 | C10: 1 | D10: Matched-exposure transfer links chamber physics to shelf-relevant quality trajectories. | E10: 9 | F10: No | G10: No | H10: 0 | K10: Not reviewed
A11: Abstract | B11: 12 | C11: 1 | D11: Acoustic technologies are increasingly applied to intact fruit for non-destructive sensing, quality modulation, drying, cleaning and related processing, yet studies often define treatment by nominal frequency, sound-pressure level, generator power and exposure time. | E11: 33 | F11: Yes | G11: Yes | H11: 3 | J11: Split or simplify; Consider active voice; Replace noun-heavy phrasing | K11: Not reviewed
A12: Abstract | B12: 12 | C12: 2 | D12: These variables describe the source but not the route-specific exposure delivered to a heterogeneous, evolving fruit. | E12: 16 | F12: No | G12: No | H12: 0 | K12: Not reviewed
A13: Abstract | B13: 12 | C13: 3 | D13: This critical review compares five physical acoustic technology families and evaluates evidence across a source–loaded-field–interface–receiver–biology–shelf chain. | E13: 21 | F13: No | G13: No | H13: 3 | J13: Replace noun-heavy phrasing | K13: Not reviewed
A14: Abstract | B14: 12 | C14: 4 | D14: The analysis shows that identical frequency bands can produce fundamentally different mechanisms, including tool-induced strain, support vibration, gas-boundary-layer forcing and liquid cavitation. | E14: 22 | F14: No | G14: No | H14: 3 | J14: Replace noun-heavy phrasing | K14: Not reviewed
A15: Abstract | B15: 12 | C15: 5 | D15: Among seven primary airborne-fruit studies retained under the stated protocol, none measured fruit motion, isolated support-mediated transfer or externally validated the physical exposure–quality relationship. | E15: 25 | F15: No | G15: No | H15: 2 | K15: Not reviewed
A16: Abstract | B16: 12 | C16: 6 | D16: Repeated phenotypic, transcriptomic, epigenetic and metabolomic associations therefore justify decisive experiments but do not establish resonance, tissue strain or mechanotransduction as the causal route. | E16: 24 | F16: No | G16: No | H16: 3 | J16: Replace noun-heavy phrasing | K16: Not reviewed
A17: Abstract | B17: 12 | C17: 7 | D17: In contrast, acoustic sensing and liquid-ultrasound research show greater maturity where excitation, transfer and receiver response are observable. | E17: 18 | F17: No | G17: No | H17: 1 | K17: Not reviewed
A18: Abstract | B18: 12 | C18: 8 | D18: We address the metrology gap through a Receiver-Centred Exposure Passport, an Acoustic Operating Window, route-separating falsification tests, sentinel-fruit monitoring and receiver-equivalence validation across equipment and loads. | E18: 26 | F18: Yes | G18: No | H18: 4 | J18: Split or simplify; Replace noun-heavy phrasing | K18: Not reviewed
A19: Abstract | B19: 12 | C19: 9 | D19: Future work should prioritize loaded-system mapping, state-dependent exposure–response boundaries, validated surface-to-tissue strain reconstruction and independent transfer under realistic storage conditions. | E19: 21 | F19: No | G19: No | H19: 1 | K19: Not reviewed
A20: Abstract | B20: 12 | C20: 10 | D20: Acoustic processing can move from empirical source recipes to shelf-relevant engineering only when researchers measure and control what the fruit actually receives. | E20: 22 | F20: No | G20: No | H20: 1 | K20: Not reviewed
A21: Abstract | B21: 13 | C21: 1 | D21: Keywords: acoustic processing; intact fruit; receiver exposure; acoustic sensing; power ultrasound; resonance; shelf life; process design | E21: 16 | F21: No | G21: No | H21: 1 | K21: Not reviewed
A22: 1. Introduction: the missing link from sound to shelf | B22: 16 | C22: 1 | D22: Consider four food-processing systems operating at 25 kHz. | E22: 8 | F22: No | G22: No | H22: 0 | K22: Not reviewed
A23: 1. Introduction: the missing link from sound to shelf | B23: 16 | C23: 2 | D23: A sonotrode transfers displacement directly into food; an ultrasonic bath generates cavitation, streaming and microjets; an airborne transducer perturbs a gas boundary layer; and a vibrating tray transfers structure-borne motion into the product. | E23: 33 | F23: Yes | G23: No | H23: 3 | J23: Split or simplify; Replace noun-heavy phrasing | K23: Not reviewed
A24: 1. Introduction: the missing link from sound to shelf | B24: 16 | C24: 3 | D24: The frequency is identical, but the energy path, receiver variable and proximal mechanism are not. | E24: 15 | F24: No | G24: No | H24: 2 | K24: Not reviewed
A25: 1. Introduction: the missing link from sound to shelf | B25: 16 | C25: 4 | D25: Hertz identifies how rapidly the source oscillates; it does not define the treatment received by the food. | E25: 17 | F25: No | G25: No | H25: 1 | K25: Not reviewed
A26: 1. Introduction: the missing link from sound to shelf | B26: 17 | C26: 1 | D26: This distinction matters acutely for intact fruit. | E26: 7 | F26: No | G26: No | H26: 1 | K26: Not reviewed
A27: 1. Introduction: the missing link from sound to shelf | B27: 17 | C27: 2 | D27: Fruit is neither a homogeneous passive solid nor a fixed biological target. | E27: 12 | F27: No | G27: No | H27: 1 | K27: Not reviewed
A28: 1. Introduction: the missing link from sound to shelf | B28: 17 | C28: 3 | D28: Geometry, peel and flesh structure, locules, seeds, turgor, temperature, support and maturity determine how an external field becomes motion, strain, heating or fluid transport. | E28: 24 | F28: No | G28: No | H28: 2 | K28: Not reviewed
A29: 1. Introduction: the missing link from sound to shelf | B29: 17 | C29: 4 | D29: These properties change during storage. | E29: 5 | F29: No | G29: No | H29: 0 | K29: Not reviewed
A30: 1. Introduction: the missing link from sound to shelf | B30: 17 | C30: 5 | D30: A fixed generator setting can therefore produce different exposures among fruit, chamber positions, batches and days, while different generators can produce similar receiver motion. | E30: 24 | F30: No | G30: No | H30: 1 | K30: Not reviewed
A31: 1. Introduction: the missing link from sound to shelf | B31: 18 | C31: 1 | D31: The literature contains the components of a stronger engineering framework, but they remain separated. | E31: 14 | F31: No | G31: No | H31: 0 | K31: Not reviewed
A32: 1. Introduction: the missing link from sound to shelf | B32: 18 | C32: 2 | D32: Modal and impulse-response studies show that fruit frequency response and damping can track firmness or maturity [14–25,75–84]. | E32: 20 | F32: No | G32: No | H32: 1 | K32: Not reviewed
A33: 1. Introduction: the missing link from sound to shelf | B33: 18 | C33: 3 | D33: A connected sequence of tomato studies reports associations between airborne sound exposure and phenotype, gases, transcripts, histone modification and metabolites [26–30]. | E33: 22 | F33: No | G33: No | H33: 2 | K33: Not reviewed
A34: 1. Introduction: the missing link from sound to shelf | B34: 18 | C34: 4 | D34: Power-ultrasound research shows that load geometry, dissolved gas, temperature and spatial field structure alter process performance [1–13,39–74]. | E34: 20 | F34: No | G34: No | H34: 2 | K34: Not reviewed
A35: 1. Introduction: the missing link from sound to shelf | B35: 18 | C35: 5 | D35: These findings establish promise, not a common process definition. | E35: 9 | F35: No | G35: No | H35: 1 | K35: Not reviewed
... A38: 1. Introduction: the missing link from sound to shelf | B38: 19 | C38: 3 | D38: They rarely measure the receiver or isolate the transfer route. | E38: 10 | F38: No | G38: No | H38: 0 | K38: Not reviewed
A39: 1. Introduction: the missing link from sound to shelf | B39: 19 | C39: 4 | D39: Among the seven primary studies retained in this review, none measured fruit motion, none isolated support-mediated transfer and none externally validated the physical exposure–quality relation. | E39: 26 | F39: Yes | G39: No | H39: 3 | J39: Split or simplify; Replace noun-heavy phrasing | K39: Not reviewed
A40: 1. Introduction: the missing link from sound to shelf | B40: 19 | C40: 5 | D40: A biological association can be real while its physical cause remains unresolved. | E40: 12 | F40: No | G40: No | H40: 3 | J40: Replace noun-heavy phrasing | K40: Not reviewed
A41: 1. Introduction: the missing link from sound to shelf | B41: 20 | C41: 1 | D41: This review takes a defensible position: a transferable acoustic process must be defined by the exposure received by the food, not by repeated source settings. | E41: 25 | F41: No | G41: Yes | H41: 1 | J41: Consider active voice | K41: Not reviewed
A42: 1. Introduction: the missing link from sound to shelf | B42: 20 | C42: 2 | D42: For a mechanically driven response, receiver motion or a validated strain proxy should predict longitudinal quality more consistently than nominal frequency, loudspeaker level or generator power. | E42: 26 | F42: Yes | G42: No | H42: 3 | J42: Split or simplify; Replace noun-heavy phrasing | K42: Not reviewed
A43: 1. Introduction: the missing link from sound to shelf | B43: 20 | C43: 3 | D43: If exposure matching does not improve prediction or transfer, the receiver-centred hypothesis is incomplete. | E43: 14 | F43: No | G43: No | H43: 1 | K43: Not reviewed
A44: 1. Introduction: the missing link from sound to shelf | B44: 21 | C44: 1 | D44: The review makes three refutable contributions: | E44: 6 | F44: No | G44: No | H44: 0 | K44: Not reviewed
A45: 1. Introduction: the missing link from sound to shelf | B45: 22 | C45: 1 | D45: Physical reclassification. | E45: 2 | F45: No | G45: No | H45: 2 | K45: Not reviewed
A46: 1. Introduction: the missing link from sound to shelf | B46: 22 | C46: 2 | D46: We show that frequency cannot define process identity because overlapping bands contain different coupling paths, mechanisms and receiver variables (Figure 1; Table 1). | E46: 23 | F46: No | G46: No | H46: 1 | K46: Not reviewed
A47: 1. Introduction: the missing link from sound to shelf | B47: 23 | C47: 1 | D47: Evidence-chain diagnosis. | E47: 2 | F47: No | G47: No | H47: 1 | K47: Not reviewed
A48: 1. Introduction: the missing link from sound to shelf | B48: 23 | C48: 2 | D48: We compare seven primary airborne-fruit studies and identify fruit motion, support isolation and external validation as the principal missing links (Table 2; Figure 3). | E48: 24 | F48: No | G48: No | H48: 5 | J48: Replace noun-heavy phrasing | K48: Not reviewed
A49: 1. Introduction: the missing link from sound to shelf | B49: 24 | C49: 1 | D49: Transferable process design. | E49: 3 | F49: No | G49: No | H49: 0 | K49: Not reviewed
A50: 1. Introduction: the missing link from sound to shelf | B50: 24 | C50: 2 | D50: We propose a Receiver-Centred Exposure Passport, an Acoustic Operating Window and matched-exposure tests that can support or reject receiver equivalence across fruit states, loads and equipment (Figure 4; Table 3). | E50: 30 | F50: Yes | G50: No | H50: 2 | J50: Split or simplify | K50: Not reviewed
A51: 2. Review scope and critical evidence method | B51: 26 | C51: 1 | D51: This article is a question-led critical review rather than a statistical meta-analysis or bibliometric survey. | E51: 15 | F51: No | G51: No | H51: 3 | J51: Replace noun-heavy phrasing | K51: Not reviewed
A52: 2. Review scope and critical evidence method | B52: 26 | C52: 2 | D52: Searches were updated through 14 September 2026 using Crossref metadata, publisher search services and backward citation tracing from major reviews. | E52: 20 | F52: No | G52: Yes | H52: 1 | J52: Consider active voice | K52: Not reviewed
A53: 2. Review scope and critical evidence method | B53: 26 | C53: 3 | D53: Query families combined fruit or named commodities with acoustic, sound, vibration, resonance, ultrasound, cavitation, firmness, ripening, quality, mechanotransduction, calcium, reactive oxygen, ethylene, sensing, state estimation, control and digital twin. | E53: 29 | F53: Yes | G53: No | H53: 6 | J53: Split or simplify; Replace noun-heavy phrasing | K53: Not reviewed
A54: 2. Review scope and critical evidence method | B54: 27 | C54: 1 | D54: We retained records when they informed at least one link in the source–loaded-field–interface–receiver–response–quality chain. | E54: 19 | F54: No | G54: No | H54: 0 | K54: Not reviewed
A55: 2. Review scope and critical evidence method | B55: 27 | C55: 2 | D55: We used plant studies only when they supplied direct physical or mechanistic evidence unavailable in intact fruit. | E55: 17 | F55: No | G55: No | H55: 2 | K55: Not reviewed
A56: 2. Review scope and critical evidence method | B56: 27 | C56: 3 | D56: Acoustic sensing, transport vibration, contact ultrasonics and liquid power ultrasound serve as mechanistically distinct comparator literatures; they do not validate airborne treatment by analogy. | E56: 24 | F56: No | G56: No | H56: 2 | K56: Not reviewed
A57: 2. Review scope and critical evidence method | B57: 28 | C57: 1 | D57: Evidence grades describe the specific link under review, not whether a reported endpoint reached statistical significance. | E57: 16 | F57: No | G57: No | H57: 3 | J57: Replace noun-heavy phrasing | K57: Not reviewed
A58: 2. Review scope and critical evidence method | B58: 28 | C58: 2 | D58: Grade A denotes direct measurement of the relevant link or externally validated prediction. | E58: 13 | F58: No | G58: No | H58: 2 | K58: Not reviewed
A59: 2. Review scope and critical evidence method | B59: 28 | C59: 3 | D59: Grade B denotes controlled evidence in a bounded system that leaves part of the transfer chain latent. | E59: 17 | F59: No | G59: No | H59: 1 | K59: Not reviewed
A60: 2. Review scope and critical evidence method | B60: 28 | C60: 4 | D60: Grade C denotes nominal or partial characterization vulnerable to coupling, order, batch or microclimate confounding. | E60: 15 | F60: No | G60: No | H60: 3 | J60: Replace noun-heavy phrasing | K60: Not reviewed
A61: 2. Review scope and critical evidence method | B61: 28 | C61: 5 | D61: Grade D denotes an unmeasured or undemonstrated link. | E61: 8 | F61: No | G61: No | H61: 0 | K61: Not reviewed
A62: 2. Review scope and critical evidence method | B62: 28 | C62: 6 | D62: A study may therefore contain strong molecular analysis and weak mechanical exposure evidence. | E62: 13 | F62: No | G62: No | H62: 2 | K62: Not reviewed
A63: 2. Review scope and critical evidence method | B63: 29 | C63: 1 | D63: The review makes corpus-bounded absence claims. | E63: 6 | F63: No | G63: No | H63: 1 | K63: Not reviewed
A64: 2. Review scope and critical evidence method | B64: 29 | C64: 2 | D64: “None of the seven studies retained here” does not mean that no relevant study can exist outside the search record. | E64: 20 | F64: No | G64: No | H64: 0 | K64: Not reviewed
A65: 2. Review scope and critical evidence method | B65: 29 | C65: 3 | D65: The complete search strings, eligibility log, study extraction and cell-level grade justifications should accompany submission as Supplementary Tables S1–S3. | E65: 20 | F65: No | G65: No | H65: 3 | J65: Replace noun-heavy phrasing | K65: Not reviewed
A66: 2. Review scope and critical evidence method | B66: 29 | C66: 4 | D66: No screening count or missing experimental detail is inferred when the source does not report it. | E66: 16 | F66: No | G66: Yes | H66: 1 | J66: Consider active voice | K66: Not reviewed
A67: 3.1 Frequency organizes sources, not effects | B67: 32 | C67: 1 | D67: The word sound hides five physical technology families: diagnostic acoustics; contact and structure-borne processing; low-intensity airborne intervention; airborne power ultrasound; and liquid power ultrasound. | E67: 24 | F67: No | G67: No | H67: 3 | J67: Replace noun-heavy phrasing | K67: Not reviewed
A68: 3.1 Frequency organizes sources, not effects | B68: 32 | C68: 2 | D68: Diagnostic acoustics contains two operational modalities—impact/resonance sensing and megahertz propagation or imaging—but both seek information from small perturbations. | E68: 21 | F68: No | G68: No | H68: 4 | J68: Replace noun-heavy phrasing | K68: Not reviewed
A69: 3.1 Frequency organizes sources, not effects | B69: 32 | C69: 3 | D69: The processing families instead transfer energy to change transport, structure, safety or quality. | E69: 13 | F69: No | G69: No | H69: 0 | K69: Not reviewed
A70: 3.1 Frequency organizes sources, not effects | B70: 33 | C70: 1 | D70: Figure 1 separates source frequency from receiver-effect regime. | E70: 8 | F70: No | G70: No | H70: 0 | K70: Not reviewed
A71: 3.1 Frequency organizes sources, not effects | B71: 33 | C71: 2 | D71: Its vertical dimension is conceptual, not a common dose axis. | E71: 10 | F71: No | G71: No | H71: 3 | J71: Replace noun-heavy phrasing | K71: Not reviewed
A72: 3.1 Frequency organizes sources, not effects | B72: 33 | C72: 3 | D72: Airborne intensity, tray acceleration, tool displacement and cavitation activity have different dimensions and cannot be collapsed without a validated transfer model. | E72: 21 | F72: No | G72: Yes | H72: 5 | J72: Consider active voice; Replace noun-heavy phrasing | K72: Not reviewed
A73: 3.1 Frequency organizes sources, not effects | B73: 33 | C73: 4 | D73: The 25 kHz slice exposes the central category error: one label can hide direct tool strain, gas-boundary-layer forcing, liquid cavitation and support motion. | E73: 23 | F73: No | G73: No | H73: 3 | J73: Replace noun-heavy phrasing | K73: Not reviewed
A74: 3.1 Frequency organizes sources, not effects | B74: 34 | C74: 1 | D74: Table 1 translates the map into process-design variables. | E74: 8 | F74: No | G74: No | H74: 0 | K74: Not reviewed
A75: 3.1 Frequency organizes sources, not effects | B75: 34 | C75: 2 | D75: The decisive column is the receiver variable: each family requires a different measurement before its outcome can be interpreted. | E75: 19 | F75: No | G75: Yes | H75: 1 | J75: Consider active voice | K75: Not reviewed
A76: 3.1 Frequency organizes sources, not effects | B76: 37 | C76: 1 | D76: Figure 1. | E76: 2 | F76: No | G76: No | H76: 0 | K76: Not reviewed
A77: 3.1 Frequency organizes sources, not effects | B77: 37 | C77: 2 | D77: One acoustic spectrum, multiple physical technologies. | E77: 6 | F77: No | G77: No | H77: 1 | K77: Not reviewed
A78: 3.1 Frequency organizes sources, not effects | B78: 37 | C78: 3 | D78: Typical frequency ranges locate source bands but do not define the receiver exposure or mechanism. | E78: 15 | F78: No | G78: No | H78: 1 | K78: Not reviewed
A79: 3.1 Frequency organizes sources, not effects | B79: 37 | C79: 4 | D79: The 25 kHz counterexample shows contact-tool strain, airborne boundary-layer forcing, liquid cavitation and structure-borne support motion under the same nominal hertz label. | E79: 22 | F79: No | G79: No | H79: 3 | J79: Replace noun-heavy phrasing | K79: Not reviewed
A80: 3.1 Frequency organizes sources, not effects | B80: 37 | C80: 5 | D80: The vertical dimension is conceptual rather than a universal dose axis. | E80: 11 | F80: No | G80: No | H80: 4 | J80: Replace noun-heavy phrasing | K80: Not reviewed
A81: 3.1 Frequency organizes sources, not effects | B81: 39 | C81: 1 | D81: Table 1. | E81: 2 | F81: No | G81: No | H81: 0 | K81: Not reviewed
A82: 3.1 Frequency organizes sources, not effects | B82: 39 | C82: 2 | D82: Acoustic technology families, defining mechanisms and receiver-centred process-design requirements. | E82: 9 | F82: No | G82: No | H82: 0 | K82: Not reviewed
A83: 3.1 Frequency organizes sources, not effects | B83: 40 | C83: 1 | D83: Frequency ranges are typical and non-prescriptive. | E83: 6 | F83: No | G83: No | H83: 1 | K83: Not reviewed
A84: 3.1 Frequency organizes sources, not effects | B84: 40 | C84: 2 | D84: “Evidence maturity” describes the literature body, not the quality of every individual study. | E84: 13 | F84: No | G84: No | H84: 2 | K84: Not reviewed
A85: 3.2 Source settings do not define receiver exposure | B85: 43 | C85: 1 | D85: Sound-pressure level converts an acoustic pressure amplitude to a logarithmic reference; it does not state how much mechanical energy enters a fruit. | E85: 22 | F85: No | G85: No | H85: 2 | K85: Not reviewed
A86: 3.2 Source settings do not define receiver exposure | B86: 43 | C86: 2 | D86: For airborne sound, | E86: 3 | F86: No | G86: No | H86: 0 | K86: Not reviewed
A87: 3.2 Source settings do not define receiver exposure | B87: 44 | C87: 1 | D87: Equation 1 | E87: 2 | F87: No | G87: No | H87: 1 | K87: Not reviewed
A88: 3.2 Source settings do not define receiver exposure | B88: 45 | C88: 1 | D88: where p_rms is root-mean-square acoustic pressure and p₀ is 20 µPa. | E88: 11 | F88: No | G88: No | H88: 0 | K88: Not reviewed
A89: 3.2 Source settings do not define receiver exposure | B89: 45 | C89: 2 | D89: Values of 80, 90, 94 and 100 dB correspond approximately to 0.20, 0.63, 1.0 and 2.0 Pa root mean square. | E89: 24 | F89: No | G89: No | H89: 0 | K89: Not reviewed
A90: 3.2 Source settings do not define receiver exposure | B90: 45 | C90: 3 | D90: Under the restrictive assumption of a progressive plane wave, incident intensity is | E90: 12 | F90: No | G90: No | H90: 2 | K90: Not reviewed
A91: 3.2 Source settings do not define receiver exposure | B91: 46 | C91: 1 | D91: Equation 2 | E91: 2 | F91: No | G91: No | H91: 1 | K91: Not reviewed
A92: 3.2 Source settings do not define receiver exposure | B92: 47 | C92: 1 | D92: At 100 dB, Equation 2 gives about 9.7 mW m⁻² in air. | E92: 14 | F92: No | G92: No | H92: 1 | K92: Not reviewed
... A94: 3.2 Source settings do not define receiver exposure | B94: 47 | C94: 3 | D94: The air-to-water-rich-tissue impedance mismatch further limits transfer. | E94: 7 | F94: No | G94: No | H94: 1 | K94: Not reviewed
A95: 3.2 Source settings do not define receiver exposure | B95: 47 | C95: 4 | D95: Curvature, peel, porosity, local compliance and structural resonance make a planar transmission coefficient an order-of-magnitude warning, not a substitute for receiver measurement. | E95: 22 | F95: No | G95: No | H95: 7 | J95: Replace noun-heavy phrasing | K95: Not reviewed
A96: 3.2 Source settings do not define receiver exposure | B96: 48 | C96: 1 | D96: The mechanically relevant airborne quantity is the time-averaged power crossing the fruit surface. | E96: 13 | F96: No | G96: No | H96: 1 | K96: Not reviewed
A97: 3.2 Source settings do not define receiver exposure | B97: 48 | C97: 2 | D97: For a contact route, the corresponding quantity is work transferred through force and contact velocity: | E97: 15 | F97: No | G97: Yes | H97: 1 | J97: Consider active voice | K97: Not reviewed
A98: 3.2 Source settings do not define receiver exposure | B98: 49 | C98: 1 | D98: Equation 3 | E98: 2 | F98: No | G98: No | H98: 1 | K98: Not reviewed
A99: 3.2 Source settings do not define receiver exposure | B99: 50 | C99: 1 | D99: These expressions expose what speaker wattage and one microphone reading omit: pressure–velocity phase, spatial nonuniformity, fruit geometry, mode shape, damping, support coupling and exposure history. | E99: 26 | F99: Yes | G99: No | H99: 2 | J99: Split or simplify | K99: Not reviewed
A100: 3.2 Source settings do not define receiver exposure | B100: 51 | C100: 1 | D100: Wavelength and acoustic size help identify the dominant confounder: | E100: 9 | F100: No | G100: No | H100: 0 | K100: Not reviewed
A101: 3.2 Source settings do not define receiver exposure | B101: 52 | C101: 1 | D101: Equation 4 | E101: 2 | F101: No | G101: No | H101: 1 | K101: Not reviewed
A102: 3.2 Source settings do not define receiver exposure | B102: 53 | C102: 1 | D102: Here, c is sound speed, f is frequency, a is a characteristic fruit radius and k = 2πf/c. | E102: 18 | F102: No | G102: Yes | H102: 0 | J102: Consider active voice | K102: Not reviewed
A103: 3.2 Source settings do not define receiver exposure | B103: 53 | C103: 2 | D103: In air near room conditions, wavelength is about 11.4 m at 30 Hz and 0.343 m at 1 kHz. | E103: 21 | F103: No | G103: No | H103: 0 | K103: Not reviewed
...

Sheet 14_Writing_Summary
A1: Section-Level Writing Quality Summary
A2: Metrics are formula-linked to the sentence-level audit. They are diagnostic signals, not substitutes for editorial judgement.
A3: Section | B3: Sentence count | C3: Word count | D3: Average words / sentence | E3: Long sentences (>25) | F3: Long sentence % | G3: Passive heuristic count | H3: Passive % | I3: Nominalizations | J3: Clutter hits | K3: Readability risk | L3: Primary editing action | M3: Status
A4: Subtitle | B4: =COUNTIF('15_Writing_Sentences'!$A$4:$A$357,A4) | C4: =SUMIF('15_Writing_Sentences'!$A$4:$A$357,A4,'15_Writing_Sentences'!$E$4:$E$357) | D4: =IFERROR(C4/B4,0) | E4: =COUNTIFS('15_Writing_Sentences'!$A$4:$A$357,A4,'15_Writing_Sentences'!$F$4:$F$357,"Yes") | F4: =IFERROR(E4/B4,0) | G4: =COUNTIFS('15_Writing_Sentences'!$A$4:$A$357,A4,'15_Writing_Sentences'!$G$4:$G$357,"Yes") | H4: =IFERROR(G4/B4,0) | I4: =SUMIF('15_Writing_Sentences'!$A$4:$A$357,A4,'15_Writing_Sentences'!$H$4:$H$357) | J4: =COUNTIFS('15_Writing_Sentences'!$A$4:$A$357,A4,'15_Writing_Sentences'!$I$4:$I$357,"<>") | K4: =IF(OR(D4>24,F4>0.3,H4>0.25),"High",IF(OR(D4>20,F4>0.2,H4>0.18),"Medium","Low")) | L4: =IF(K4="High","Prioritize sentence splitting, active voice and clutter removal",IF(K4="Medium","Target long / passive sentences","Light polish")) | M4: Not reviewed
A5: Highlights | B5: =COUNTIF('15_Writing_Sentences'!$A$4:$A$357,A5) | C5: =SUMIF('15_Writing_Sentences'!$A$4:$A$357,A5,'15_Writing_Sentences'!$E$4:$E$357) | D5: =IFERROR(C5/B5,0) | E5: =COUNTIFS('15_Writing_Sentences'!$A$4:$A$357,A5,'15_Writing_Sentences'!$F$4:$F$357,"Yes") | F5: =IFERROR(E5/B5,0) | G5: =COUNTIFS('15_Writing_Sentences'!$A$4:$A$357,A5,'15_Writing_Sentences'!$G$4:$G$357,"Yes") | H5: =IFERROR(G5/B5,0) | I5: =SUMIF('15_Writing_Sentences'!$A$4:$A$357,A5,'15_Writing_Sentences'!$H$4:$H$357) | J5: =COUNTIFS('15_Writing_Sentences'!$A$4:$A$357,A5,'15_Writing_Sentences'!$I$4:$I$357,"<>") | K5: =IF(OR(D5>24,F5>0.3,H5>0.25),"High",IF(OR(D5>20,F5>0.2,H5>0.18),"Medium","Low")) | L5: =IF(K5="High","Prioritize sentence splitting, active voice and clutter removal",IF(K5="Medium","Target long / passive sentences","Light polish")) | M5: Not reviewed
A6: Abstract | B6: =COUNTIF('15_Writing_Sentences'!$A$4:$A$357,A6) | C6: =SUMIF('15_Writing_Sentences'!$A$4:$A$357,A6,'15_Writing_Sentences'!$E$4:$E$357) | D6: =IFERROR(C6/B6,0) | E6: =COUNTIFS('15_Writing_Sentences'!$A$4:$A$357,A6,'15_Writing_Sentences'!$F$4:$F$357,"Yes") | F6: =IFERROR(E6/B6,0) | G6: =COUNTIFS('15_Writing_Sentences'!$A$4:$A$357,A6,'15_Writing_Sentences'!$G$4:$G$357,"Yes") | H6: =IFERROR(G6/B6,0) | I6: =SUMIF('15_Writing_Sentences'!$A$4:$A$357,A6,'15_Writing_Sentences'!$H$4:$H$357) | J6: =COUNTIFS('15_Writing_Sentences'!$A$4:$A$357,A6,'15_Writing_Sentences'!$I$4:$I$357,"<>") | K6: =IF(OR(D6>24,F6>0.3,H6>0.25),"High",IF(OR(D6>20,F6>0.2,H6>0.18),"Medium","Low")) | L6: =IF(K6="High","Prioritize sentence splitting, active voice and clutter removal",IF(K6="Medium","Target long / passive sentences","Light polish")) | M6: Not reviewed
A7: 1. Introduction: the missing link from sound to shelf | B7: =COUNTIF('15_Writing_Sentences'!$A$4:$A$357,A7) | C7: =SUMIF('15_Writing_Sentences'!$A$4:$A$357,A7,'15_Writing_Sentences'!$E$4:$E$357) | D7: =IFERROR(C7/B7,0) | E7: =COUNTIFS('15_Writing_Sentences'!$A$4:$A$357,A7,'15_Writing_Sentences'!$F$4:$F$357,"Yes") | F7: =IFERROR(E7/B7,0) | G7: =COUNTIFS('15_Writing_Sentences'!$A$4:$A$357,A7,'15_Writing_Sentences'!$G$4:$G$357,"Yes") | H7: =IFERROR(G7/B7,0) | I7: =SUMIF('15_Writing_Sentences'!$A$4:$A$357,A7,'15_Writing_Sentences'!$H$4:$H$357) | J7: =COUNTIFS('15_Writing_Sentences'!$A$4:$A$357,A7,'15_Writing_Sentences'!$I$4:$I$357,"<>") | K7: =IF(OR(D7>24,F7>0.3,H7>0.25),"High",IF(OR(D7>20,F7>0.2,H7>0.18),"Medium","Low")) | L7: =IF(K7="High","Prioritize sentence splitting, active voice and clutter removal",IF(K7="Medium","Target long / passive sentences","Light polish")) | M7: Not reviewed
A8: 2. Review scope and critical evidence method | B8: =COUNTIF('15_Writing_Sentences'!$A$4:$A$357,A8) | C8: =SUMIF('15_Writing_Sentences'!$A$4:$A$357,A8,'15_Writing_Sentences'!$E$4:$E$357) | D8: =IFERROR(C8/B8,0) | E8: =COUNTIFS('15_Writing_Sentences'!$A$4:$A$357,A8,'15_Writing_Sentences'!$F$4:$F$357,"Yes") | F8: =IFERROR(E8/B8,0) | G8: =COUNTIFS('15_Writing_Sentences'!$A$4:$A$357,A8,'15_Writing_Sentences'!$G$4:$G$357,"Yes") | H8: =IFERROR(G8/B8,0) | I8: =SUMIF('15_Writing_Sentences'!$A$4:$A$357,A8,'15_Writing_Sentences'!$H$4:$H$357) | J8: =COUNTIFS('15_Writing_Sentences'!$A$4:$A$357,A8,'15_Writing_Sentences'!$I$4:$I$357,"<>") | K8: =IF(OR(D8>24,F8>0.3,H8>0.25),"High",IF(OR(D8>20,F8>0.2,H8>0.18),"Medium","Low")) | L8: =IF(K8="High","Prioritize sentence splitting, active voice and clutter removal",IF(K8="Medium","Target long / passive sentences","Light polish")) | M8: Not reviewed
A9: 3.1 Frequency organizes sources, not effects | B9: =COUNTIF('15_Writing_Sentences'!$A$4:$A$357,A9) | C9: =SUMIF('15_Writing_Sentences'!$A$4:$A$357,A9,'15_Writing_Sentences'!$E$4:$E$357) | D9: =IFERROR(C9/B9,0) | E9: =COUNTIFS('15_Writing_Sentences'!$A$4:$A$357,A9,'15_Writing_Sentences'!$F$4:$F$357,"Yes") | F9: =IFERROR(E9/B9,0) | G9: =COUNTIFS('15_Writing_Sentences'!$A$4:$A$357,A9,'15_Writing_Sentences'!$G$4:$G$357,"Yes") | H9: =IFERROR(G9/B9,0) | I9: =SUMIF('15_Writing_Sentences'!$A$4:$A$357,A9,'15_Writing_Sentences'!$H$4:$H$357) | J9: =COUNTIFS('15_Writing_Sentences'!$A$4:$A$357,A9,'15_Writing_Sentences'!$I$4:$I$357,"<>") | K9: =IF(OR(D9>24,F9>0.3,H9>0.25),"High",IF(OR(D9>20,F9>0.2,H9>0.18),"Medium","Low")) | L9: =IF(K9="High","Prioritize sentence splitting, active voice and clutter removal",IF(K9="Medium","Target long / passive sentences","Light polish")) | M9: Not reviewed
A10: 3.2 Source settings do not define receiver exposure | B10: =COUNTIF('15_Writing_Sentences'!$A$4:$A$357,A10) | C10: =SUMIF('15_Writing_Sentences'!$A$4:$A$357,A10,'15_Writing_Sentences'!$E$4:$E$357) | D10: =IFERROR(C10/B10,0) | E10: =COUNTIFS('15_Writing_Sentences'!$A$4:$A$357,A10,'15_Writing_Sentences'!$F$4:$F$357,"Yes") | F10: =IFERROR(E10/B10,0) | G10: =COUNTIFS('15_Writing_Sentences'!$A$4:$A$357,A10,'15_Writing_Sentences'!$G$4:$G$357,"Yes") | H10: =IFERROR(G10/B10,0) | I10: =SUMIF('15_Writing_Sentences'!$A$4:$A$357,A10,'15_Writing_Sentences'!$H$4:$H$357) | J10: =COUNTIFS('15_Writing_Sentences'!$A$4:$A$357,A10,'15_Writing_Sentences'!$I$4:$I$357,"<>") | K10: =IF(OR(D10>24,F10>0.3,H10>0.25),"High",IF(OR(D10>20,F10>0.2,H10>0.18),"Medium","Low")) | L10: =IF(K10="High","Prioritize sentence splitting, active voice and clutter removal",IF(K10="Medium","Target long / passive sentences","Light polish")) | M10: Not reviewed
A11: 3.3 Fruit is an evolving receiver | B11: =COUNTIF('15_Writing_Sentences'!$A$4:$A$357,A11) | C11: =SUMIF('15_Writing_Sentences'!$A$4:$A$357,A11,'15_Writing_Sentences'!$E$4:$E$357) | D11: =IFERROR(C11/B11,0) | E11: =COUNTIFS('15_Writing_Sentences'!$A$4:$A$357,A11,'15_Writing_Sentences'!$F$4:$F$357,"Yes") | F11: =IFERROR(E11/B11,0) | G11: =COUNTIFS('15_Writing_Sentences'!$A$4:$A$357,A11,'15_Writing_Sentences'!$G$4:$G$357,"Yes") | H11: =IFERROR(G11/B11,0) | I11: =SUMIF('15_Writing_Sentences'!$A$4:$A$357,A11,'15_Writing_Sentences'!$H$4:$H$357) | J11: =COUNTIFS('15_Writing_Sentences'!$A$4:$A$357,A11,'15_Writing_Sentences'!$I$4:$I$357,"<>") | K11: =IF(OR(D11>24,F11>0.3,H11>0.25),"High",IF(OR(D11>20,F11>0.2,H11>0.18),"Medium","Low")) | L11: =IF(K11="High","Prioritize sentence splitting, active voice and clutter removal",IF(K11="Medium","Target long / passive sentences","Light polish")) | M11: Not reviewed
A12: 3.4 Per-fruit and sentinel state estimation | B12: =COUNTIF('15_Writing_Sentences'!$A$4:$A$357,A12) | C12: =SUMIF('15_Writing_Sentences'!$A$4:$A$357,A12,'15_Writing_Sentences'!$E$4:$E$357) | D12: =IFERROR(C12/B12,0) | E12: =COUNTIFS('15_Writing_Sentences'!$A$4:$A$357,A12,'15_Writing_Sentences'!$F$4:$F$357,"Yes") | F12: =IFERROR(E12/B12,0) | G12: =COUNTIFS('15_Writing_Sentences'!$A$4:$A$357,A12,'15_Writing_Sentences'!$G$4:$G$357,"Yes") | H12: =IFERROR(G12/B12,0) | I12: =SUMIF('15_Writing_Sentences'!$A$4:$A$357,A12,'15_Writing_Sentences'!$H$4:$H$357) | J12: =COUNTIFS('15_Writing_Sentences'!$A$4:$A$357,A12,'15_Writing_Sentences'!$I$4:$I$357,"<>") | K12: =IF(OR(D12>24,F12>0.3,H12>0.25),"High",IF(OR(D12>20,F12>0.2,H12>0.18),"Medium","Low")) | L12: =IF(K12="High","Prioritize sentence splitting, active voice and clutter removal",IF(K12="Medium","Target long / passive sentences","Light polish")) | M12: Not reviewed
A13: 4.1 Airborne effects on intact fruit: a connected evidence lineage | B13: =COUNTIF('15_Writing_Sentences'!$A$4:$A$357,A13) | C13: =SUMIF('15_Writing_Sentences'!$A$4:$A$357,A13,'15_Writing_Sentences'!$E$4:$E$357) | D13: =IFERROR(C13/B13,0) | E13: =COUNTIFS('15_Writing_Sentences'!$A$4:$A$357,A13,'15_Writing_Sentences'!$F$4:$F$357,"Yes") | F13: =IFERROR(E13/B13,0) | G13: =COUNTIFS('15_Writing_Sentences'!$A$4:$A$357,A13,'15_Writing_Sentences'!$G$4:$G$357,"Yes") | H13: =IFERROR(G13/B13,0) | I13: =SUMIF('15_Writing_Sentences'!$A$4:$A$357,A13,'15_Writing_Sentences'!$H$4:$H$357) | J13: =COUNTIFS('15_Writing_Sentences'!$A$4:$A$357,A13,'15_Writing_Sentences'!$I$4:$I$357,"<>") | K13: =IF(OR(D13>24,F13>0.3,H13>0.25),"High",IF(OR(D13>20,F13>0.2,H13>0.18),"Medium","Low")) | L13: =IF(K13="High","Prioritize sentence splitting, active voice and clutter removal",IF(K13="Medium","Target long / passive sentences","Light polish")) | M13: Not reviewed
A14: 4.2 Adjacent plant and transport evidence | B14: =COUNTIF('15_Writing_Sentences'!$A$4:$A$357,A14) | C14: =SUMIF('15_Writing_Sentences'!$A$4:$A$357,A14,'15_Writing_Sentences'!$E$4:$E$357) | D14: =IFERROR(C14/B14,0) | E14: =COUNTIFS('15_Writing_Sentences'!$A$4:$A$357,A14,'15_Writing_Sentences'!$F$4:$F$357,"Yes") | F14: =IFERROR(E14/B14,0) | G14: =COUNTIFS('15_Writing_Sentences'!$A$4:$A$357,A14,'15_Writing_Sentences'!$G$4:$G$357,"Yes") | H14: =IFERROR(G14/B14,0) | I14: =SUMIF('15_Writing_Sentences'!$A$4:$A$357,A14,'15_Writing_Sentences'!$H$4:$H$357) | J14: =COUNTIFS('15_Writing_Sentences'!$A$4:$A$357,A14,'15_Writing_Sentences'!$I$4:$I$357,"<>") | K14: =IF(OR(D14>24,F14>0.3,H14>0.25),"High",IF(OR(D14>20,F14>0.2,H14>0.18),"Medium","Low")) | L14: =IF(K14="High","Prioritize sentence splitting, active voice and clutter removal",IF(K14="Medium","Target long / passive sentences","Light polish")) | M14: Not reviewed
A15: 4.3 Acoustic sensing supplies the strongest industrial comparator | B15: =COUNTIF('15_Writing_Sentences'!$A$4:$A$357,A15) | C15: =SUMIF('15_Writing_Sentences'!$A$4:$A$357,A15,'15_Writing_Sentences'!$E$4:$E$357) | D15: =IFERROR(C15/B15,0) | E15: =COUNTIFS('15_Writing_Sentences'!$A$4:$A$357,A15,'15_Writing_Sentences'!$F$4:$F$357,"Yes") | F15: =IFERROR(E15/B15,0) | G15: =COUNTIFS('15_Writing_Sentences'!$A$4:$A$357,A15,'15_Writing_Sentences'!$G$4:$G$357,"Yes") | H15: =IFERROR(G15/B15,0) | I15: =SUMIF('15_Writing_Sentences'!$A$4:$A$357,A15,'15_Writing_Sentences'!$H$4:$H$357) | J15: =COUNTIFS('15_Writing_Sentences'!$A$4:$A$357,A15,'15_Writing_Sentences'!$I$4:$I$357,"<>") | K15: =IF(OR(D15>24,F15>0.3,H15>0.25),"High",IF(OR(D15>20,F15>0.2,H15>0.18),"Medium","Low")) | L15: =IF(K15="High","Prioritize sentence splitting, active voice and clutter removal",IF(K15="Medium","Target long / passive sentences","Light polish")) | M15: Not reviewed
... A41: Acknowledgements | B41: =COUNTIF('15_Writing_Sentences'!$A$4:$A$357,A41) | C41: =SUMIF('15_Writing_Sentences'!$A$4:$A$357,A41,'15_Writing_Sentences'!$E$4:$E$357) | D41: =IFERROR(C41/B41,0) | E41: =COUNTIFS('15_Writing_Sentences'!$A$4:$A$357,A41,'15_Writing_Sentences'!$F$4:$F$357,"Yes") | F41: =IFERROR(E41/B41,0) | G41: =COUNTIFS('15_Writing_Sentences'!$A$4:$A$357,A41,'15_Writing_Sentences'!$G$4:$G$357,"Yes") | H41: =IFERROR(G41/B41,0) | I41: =SUMIF('15_Writing_Sentences'!$A$4:$A$357,A41,'15_Writing_Sentences'!$H$4:$H$357) | J41: =COUNTIFS('15_Writing_Sentences'!$A$4:$A$357,A41,'15_Writing_Sentences'!$I$4:$I$357,"<>") | K41: =IF(OR(D41>24,F41>0.3,H41>0.25),"High",IF(OR(D41>20,F41>0.2,H41>0.18),"Medium","Low")) | L41: =IF(K41="High","Prioritize sentence splitting, active voice and clutter removal",IF(K41="Medium","Target long / passive sentences","Light polish")) | M41: Not reviewed

Sheet 16_Action_Plan
A1: Prioritized Pre-Submission Action Plan
A2: Complete Critical blockers first. The plan focuses on evidence integrity before language polish.
A3: Action ID | B3: Category | C3: Action | D3: Why it matters | E3: Dependency | F3: Impact (1–5) | G3: Effort (1–5) | H3: Urgency (1–5) | I3: Priority index | J3: Priority | K3: Owner | L3: Status | M3: Due date | N3: Evidence of completion | O3: Linked sheet / item | P3: Notes
A4: A01 | B4: Review method | C4: Complete final database searches, exact strings, dates and record counts. | D4: Supports corpus completeness and 0/7 claim. | E4: Access to databases / search exports | F4: 5 | G4: 4 | H4: 5 | I4: =ROUND((F4*H4)/MAX(G4,1),2) | J4: Critical | L4: Not started | N4: Search log + S1 populated | O4: 02 / S1
A5: A02 | B5: Evidence audit | C5: Independently verify all seven studies and every A–D cell with source pages. | D5: Makes the evidence heatmap auditable. | E5: Full texts + second reviewer | F5: 5 | G5: 4 | H5: 5 | I5: =ROUND((F5*H5)/MAX(G5,1),2) | J5: Critical | L5: Not started | N5: Signed coding log + S3 | O5: 06 / Table 2 / Fig 3
A6: A03 | B6: Reference integrity | C6: Verify all 127 citations, DOIs and claim support. | D6: Prevents unsupported or mis-cited claims. | E6: Reference manager / full texts | F6: 5 | G6: 5 | H6: 4 | I6: =ROUND((F6*H6)/MAX(G6,1),2) | J6: Critical | L6: In progress | N6: Reference Audit complete | O6: 12
A7: A04 | B7: Novelty positioning | C7: Add a concise comparison with existing acoustic / ultrasound reviews. | D7: Reduces desk-rejection risk for perceived overlap. | E7: Reference audit | F7: 5 | G7: 2 | H7: 4 | I7: =ROUND((F7*H7)/MAX(G7,1),2) | J7: High | L7: Not started | N7: Novelty paragraph / comparison box | O7: 02 S06
A8: A05 | B8: Industrial claims | C8: Define maturity criteria or soften adoption statements. | D8: Avoids overgeneralization from selected examples. | E8: Comparator and market evidence | F8: 4 | G8: 2 | H8: 4 | I8: =ROUND((F8*H8)/MAX(G8,1),2) | J8: High | L8: Not started | N8: Revised text + criteria | O8: 04 C19
A9: A06 | B9: Shelf claims | C9: Replace unsupported “shelf-life extension” language with shelf-relevant trajectories unless validated. | D9: Aligns title promise with evidence. | E9: Claim audit | F9: 5 | G9: 2 | H9: 4 | I9: =ROUND((F9*H9)/MAX(G9,1),2) | J9: High | L9: In progress | N9: Revised Section 7 | O9: 03 Section 7
A10: A07 | B10: Figures | C10: Finalize Figure 3 only after evidence coding; simplify Figure 2 and 4. | D10: Visuals carry the central scientific contribution. | E10: A02 | F10: 5 | G10: 3 | H10: 4 | I10: =ROUND((F10*H10)/MAX(G10,1),2) | J10: Critical | L10: Not started | N10: Final editable figures + captions | O10: 09
A11: A08 | B11: Tables | C11: Complete main Table 2 and Supplement S2–S3 from full texts. | D11: Comparative and causal evidence depend on complete extraction. | E11: A02 | F11: 5 | G11: 4 | H11: 5 | I11: =ROUND((F11*H11)/MAX(G11,1),2) | J11: Critical | L11: Not started | N11: Verified extraction tables | O11: 10
A12: A09 | B12: Experiment protocol | C12: Complete pilot variance, sample-size basis, equivalence margin and statistical model. | D12: Makes receiver equivalence implementable. | E12: Pilot data / statistician | F12: 4 | G12: 5 | H12: 3 | I12: =ROUND((F12*H12)/MAX(G12,1),2) | J12: High | L12: Not started | N12: Final Table S5 | O12: 08 G05 / 10 S5
A13: A10 | B13: Journal compliance | C13: Verify live TIFS article type, word/visual limits and artwork requirements. | D13: Prevents administrative rejection. | E13: Current Guide / Editorial Manager | F13: 5 | G13: 1 | H13: 5 | I13: =ROUND((F13*H13)/MAX(G13,1),2) | J13: Critical | L13: Not started | N13: Compliance record / screenshots | O13: 13
A14: A11 | B14: Declarations | C14: Complete authors, CRediT, funding, COI, AI declaration and acknowledgements. | D14: Mandatory submission package. | E14: Co-author input | F14: 5 | G14: 2 | H14: 5 | I14: =ROUND((F14*H14)/MAX(G14,1),2) | J14: Critical | L14: Not started | N14: Approved declarations | O14: 13
A15: A12 | B15: Repository | C15: Archive search records, grades, extraction tables and editable figures. | D15: Supports transparency and data availability. | E15: A01–A03 | F15: 4 | G15: 3 | H15: 3 | I15: =ROUND((F15*H15)/MAX(G15,1),2) | J15: High | L15: Not started | N15: Persistent repository link | O15: 13 J20
... A17: A14 | B17: External review | C17: Obtain feedback from acoustic metrologist, postharvest scientist, review-method expert and process engineer. | D17: Tests comprehension, fairness and feasibility. | E17: Near-final draft | F17: 5 | G17: 3 | H17: 3 | I17: =ROUND((F17*H17)/MAX(G17,1),2) | J17: High | L17: Not started | N17: Comment log + resolved actions | O17: 17 / coauthor review

Sheet 17_Decision_Log
A1: Scientific and Editorial Decision Log
A2: Use this sheet to prevent repeated scope drift and conflicting co-author edits.
A3: Decision ID | B3: Decision | C3: Rationale | D3: Alternatives rejected | E3: Scientific consequence | F3: Date | G3: Decision owner | H3: Status | I3: Revisit trigger | J3: Linked section / figure | K3: Notes | L3: Approved by
A4: D01 | B4: Use intact fruit as the focal receiver. | C4: Keeps the evidence base bounded and food-engineering relevant. | D4: Full review of all food acoustic applications. | E4: Comparator fields inform mechanism but do not redefine scope. | F4: 46293 | G4: Lead author | H4: Complete | I4: New evidence justifies wider receiver scope. | J4: Title / abstract / Section 2
A5: D02 | B5: Keep light/optical processing outside the main review. | C5: Optical dosimetry requires a separate search and mechanism framework. | D5: Add light as co-equal modality. | E5: Mention only as future transferability test, if at all. | F5: 46293 | G5: Lead author | H5: Complete | I5: Separate optical review is commissioned. | J5: Scope
A6: D03 | B6: Use three headline contributions only. | C6: Preserves one clear “ping” and avoids feature-list storytelling. | D6: List Passport, Window, sentinels and digital twin as separate innovations. | E6: All tools become implementation layers of receiver-centred process design. | F6: 46293 | G6: Lead author | H6: Complete | I6: Editor requests different framing. | J6: Introduction
A7: D04 | B7: Use 4 main figures + 3 main tables. | C7: Conservative, non-duplicative package that carries the full argument. | D7: 8 figures + 7 tables. | E7: Detailed methods move to supplement. | F7: 46293 | G7: Lead author | H7: Complete | I7: Live TIFS instructions require another format. | J7: Figures / tables
A8: D05 | B8: Use 2 supplementary figures + 5 supplementary tables. | C8: Supplement proves search, evidence coding and experiment reproducibility. | D8: Large internal planning package. | E8: Removes editorial notes and duplicated visuals. | F8: 46293 | G8: Lead author | H8: Complete | I8: Methodology expands materially. | J8: Supplement
A9: D06 | B9: Position digital twin downstream of physical validation. | C9: An advanced estimator cannot repair an unidentified transfer route. | D9: Make AI / digital twin a headline contribution. | E9: Prevents speculative scope creep. | F9: 46293 | G9: Lead author | H9: Complete | I9: Closed-loop experimental evidence emerges. | J9: Section 7.5
A10: D07 | B10: Use corpus-bounded 0/7 wording. | C10: Search is question-led and final screening records remain pending. | D10: “No study in the field…” | E10: Protects evidential honesty. | F10: 46293 | G10: Lead author | H10: Complete | I10: Completed systematic search changes denominator. | J10: Abstract / Figure 3
A11: D08 | B11: Treat receiver equivalence as a falsifiable hypothesis, not a validated fact. | C11: No cross-platform experiment has yet demonstrated it. | D11: Present as established process definition. | E11: Requires explicit pass/fail experiment. | F11: 46293 | G11: Lead author | H11: Complete | I11: Experimental validation is completed. | J11: Figure 4 / Section 8

Sheet Lists
A1: Status | C1: Priority | E1: EvidenceType | G1: YesNoPartial | I1: Grade | K1: Score | M1: Grade | N1: Numeric | P1: Status | Q1: Completion
A2: Not started | C2: Critical | E2: Direct measurement | G2: Yes | I2: A | K2: 0 | M2: A | N2: 4 | P2: Not started | Q2: 0
A3: In progress | C3: High | E3: Supported association | G3: Partial | I3: B | K3: 1 | M3: B | N3: 3 | P3: In progress | Q3: 0.4
A4: Needs verification | C4: Medium | E4: Evidence-based inference | G4: No | I4: C | K4: 2 | M4: C | N4: 2 | P4: Needs verification | Q4: 0.5
A5: Needs revision | C5: Low | E5: Testable hypothesis | G5: Not applicable | I5: D | K5: 3 | M5: D | N5: 1 | P5: Needs revision | Q5: 0.6
A6: Complete | E6: Speculation | K6: 4 | P6: Complete | Q6: 1
A7: Not applicable | P7: Not applicable | Q7: 1
